{"hierarchy":{"paths":[["doc:\/\/net.doo.ScanbotSDK\/documentation\/ScanbotSDK","doc:\/\/net.doo.ScanbotSDK\/documentation\/ScanbotSDK\/SBSDKUI2DocumentDataExtractorScreenConfiguration"]]},"schemaVersion":{"major":0,"patch":0,"minor":3},"sections":[],"primaryContentSections":[{"declarations":[{"platforms":["iOS"],"tokens":[{"kind":"text","text":"- ("},{"preciseIdentifier":"c:*Qo","kind":"typeIdentifier","text":"id"},{"kind":"text","text":") "},{"kind":"identifier","text":"initWithVersion:"},{"kind":"text","text":"("},{"preciseIdentifier":"c:objc(cs)NSString","kind":"typeIdentifier","text":"NSString"},{"kind":"text","text":" *) "},{"kind":"internalParam","text":"version"},{"kind":"text","text":" "},{"kind":"identifier","text":"screen:"},{"kind":"text","text":"("},{"preciseIdentifier":"c:objc(cs)NSString","kind":"typeIdentifier","text":"NSString"},{"kind":"text","text":" *) "},{"kind":"internalParam","text":"screen"},{"kind":"text","text":" "},{"kind":"identifier","text":"localization:"},{"kind":"text","text":"("},{"preciseIdentifier":"c:@M@ScanbotSDK@objc(cs)SBSDKUI2DocumentDataExtractorScreenTextLocalization","identifier":"doc:\/\/net.doo.ScanbotSDK\/documentation\/ScanbotSDK\/SBSDKUI2DocumentDataExtractorScreenTextLocalization","kind":"typeIdentifier","text":"SBSDKUI2DocumentDataExtractorScreenTextLocalization"},{"kind":"text","text":" *) "},{"kind":"internalParam","text":"localization"},{"kind":"text","text":" "},{"kind":"identifier","text":"palette:"},{"kind":"text","text":"("},{"preciseIdentifier":"c:@M@ScanbotSDK@objc(cs)SBSDKUI2Palette","identifier":"doc:\/\/net.doo.ScanbotSDK\/documentation\/ScanbotSDK\/SBSDKUI2Palette","kind":"typeIdentifier","text":"SBSDKUI2Palette"},{"kind":"text","text":" *) "},{"kind":"internalParam","text":"palette"},{"kind":"text","text":" "},{"kind":"identifier","text":"backgroundColor:"},{"kind":"text","text":"("},{"preciseIdentifier":"c:@M@ScanbotSDK@objc(cs)SBSDKUI2Color","identifier":"doc:\/\/net.doo.ScanbotSDK\/documentation\/ScanbotSDK\/SBSDKUI2Color","kind":"typeIdentifier","text":"SBSDKUI2Color"},{"kind":"text","text":" *) "},{"kind":"internalParam","text":"backgroundColor"},{"kind":"text","text":" "},{"kind":"identifier","text":"cameraConfiguration:"},{"kind":"text","text":"("},{"preciseIdentifier":"c:@M@ScanbotSDK@objc(cs)SBSDKUI2CameraConfiguration","identifier":"doc:\/\/net.doo.ScanbotSDK\/documentation\/ScanbotSDK\/SBSDKUI2CameraConfiguration","kind":"typeIdentifier","text":"SBSDKUI2CameraConfiguration"},{"kind":"text","text":" *) "},{"kind":"internalParam","text":"cameraConfiguration"},{"kind":"text","text":" "},{"kind":"identifier","text":"cameraPermission:"},{"kind":"text","text":"("},{"preciseIdentifier":"c:@M@ScanbotSDK@objc(cs)SBSDKUI2CameraPermissionScreen","identifier":"doc:\/\/net.doo.ScanbotSDK\/documentation\/ScanbotSDK\/SBSDKUI2CameraPermissionScreen","kind":"typeIdentifier","text":"SBSDKUI2CameraPermissionScreen"},{"kind":"text","text":" *) "},{"kind":"internalParam","text":"cameraPermission"},{"kind":"text","text":" "},{"kind":"identifier","text":"topUserGuidance:"},{"kind":"text","text":"("},{"preciseIdentifier":"c:@M@ScanbotSDK@objc(cs)SBSDKUI2UserGuidanceConfiguration","identifier":"doc:\/\/net.doo.ScanbotSDK\/documentation\/ScanbotSDK\/SBSDKUI2UserGuidanceConfiguration","kind":"typeIdentifier","text":"SBSDKUI2UserGuidanceConfiguration"},{"kind":"text","text":" *) "},{"kind":"internalParam","text":"topUserGuidance"},{"kind":"text","text":" "},{"kind":"identifier","text":"scanStatusUserGuidance:"},{"kind":"text","text":"("},{"preciseIdentifier":"c:@M@ScanbotSDK@objc(cs)SBSDKUI2DocumentDataExtractorGuidanceConfiguration","identifier":"doc:\/\/net.doo.ScanbotSDK\/documentation\/ScanbotSDK\/SBSDKUI2DocumentDataExtractorGuidanceConfiguration","kind":"typeIdentifier","text":"SBSDKUI2DocumentDataExtractorGuidanceConfiguration"},{"kind":"text","text":" *) "},{"kind":"internalParam","text":"scanStatusUserGuidance"},{"kind":"text","text":" "},{"kind":"identifier","text":"topBar:"},{"kind":"text","text":"("},{"preciseIdentifier":"c:@M@ScanbotSDK@objc(cs)SBSDKUI2TopBarConfiguration","identifier":"doc:\/\/net.doo.ScanbotSDK\/documentation\/ScanbotSDK\/SBSDKUI2TopBarConfiguration","kind":"typeIdentifier","text":"SBSDKUI2TopBarConfiguration"},{"kind":"text","text":" *) "},{"kind":"internalParam","text":"topBar"},{"kind":"text","text":" "},{"kind":"identifier","text":"topBarOpenIntroScreenButton:"},{"kind":"text","text":"("},{"preciseIdentifier":"c:@M@ScanbotSDK@objc(cs)SBSDKUI2IconButton","identifier":"doc:\/\/net.doo.ScanbotSDK\/documentation\/ScanbotSDK\/SBSDKUI2IconButton","kind":"typeIdentifier","text":"SBSDKUI2IconButton"},{"kind":"text","text":" *) "},{"kind":"internalParam","text":"topBarOpenIntroScreenButton"},{"kind":"text","text":" "},{"kind":"identifier","text":"introScreen:"},{"kind":"text","text":"("},{"preciseIdentifier":"c:@M@ScanbotSDK@objc(cs)SBSDKUI2DocumentDataExtractorIntroScreenConfiguration","identifier":"doc:\/\/net.doo.ScanbotSDK\/documentation\/ScanbotSDK\/SBSDKUI2DocumentDataExtractorIntroScreenConfiguration","kind":"typeIdentifier","text":"SBSDKUI2DocumentDataExtractorIntroScreenConfiguration"},{"kind":"text","text":" *) "},{"kind":"internalParam","text":"introScreen"},{"kind":"text","text":" "},{"kind":"identifier","text":"actionBar:"},{"kind":"text","text":"("},{"preciseIdentifier":"c:@M@ScanbotSDK@objc(cs)SBSDKUI2ActionBarConfiguration","identifier":"doc:\/\/net.doo.ScanbotSDK\/documentation\/ScanbotSDK\/SBSDKUI2ActionBarConfiguration","kind":"typeIdentifier","text":"SBSDKUI2ActionBarConfiguration"},{"kind":"text","text":" *) "},{"kind":"internalParam","text":"actionBar"},{"kind":"text","text":" "},{"kind":"identifier","text":"viewFinder:"},{"kind":"text","text":"("},{"preciseIdentifier":"c:@M@ScanbotSDK@objc(cs)SBSDKUI2PermanentViewFinderConfiguration","identifier":"doc:\/\/net.doo.ScanbotSDK\/documentation\/ScanbotSDK\/SBSDKUI2PermanentViewFinderConfiguration","kind":"typeIdentifier","text":"SBSDKUI2PermanentViewFinderConfiguration"},{"kind":"text","text":" *) "},{"kind":"internalParam","text":"viewFinder"},{"kind":"text","text":" "},{"kind":"identifier","text":"scannerConfiguration:"},{"kind":"text","text":"("},{"preciseIdentifier":"c:@M@ScanbotSDK@objc(cs)SBSDKDocumentDataExtractorConfiguration","identifier":"doc:\/\/net.doo.ScanbotSDK\/documentation\/ScanbotSDK\/SBSDKDocumentDataExtractorConfiguration","kind":"typeIdentifier","text":"SBSDKDocumentDataExtractorConfiguration"},{"kind":"text","text":" *) "},{"kind":"internalParam","text":"scannerConfiguration"},{"kind":"text","text":" "},{"kind":"identifier","text":"extractionProgress:"},{"kind":"text","text":"("},{"preciseIdentifier":"c:@M@ScanbotSDK@objc(cs)SBSDKUI2DocumentDataExtractionProgressConfiguration","identifier":"doc:\/\/net.doo.ScanbotSDK\/documentation\/ScanbotSDK\/SBSDKUI2DocumentDataExtractionProgressConfiguration","kind":"typeIdentifier","text":"SBSDKUI2DocumentDataExtractionProgressConfiguration"},{"kind":"text","text":" *) "},{"kind":"internalParam","text":"extractionProgress"},{"kind":"text","text":" "},{"kind":"identifier","text":"noDocumentFoundTimeout:"},{"kind":"text","text":"("},{"preciseIdentifier":"c:@T@NSInteger","kind":"typeIdentifier","text":"NSInteger"},{"kind":"text","text":") "},{"kind":"internalParam","text":"noDocumentFoundTimeout"},{"kind":"text","text":" "},{"kind":"identifier","text":"accumulationTimeout:"},{"kind":"text","text":"("},{"preciseIdentifier":"c:@T@NSInteger","kind":"typeIdentifier","text":"NSInteger"},{"kind":"text","text":") "},{"kind":"internalParam","text":"accumulationTimeout"},{"kind":"text","text":" "},{"kind":"identifier","text":"successOverlay:"},{"kind":"text","text":"("},{"preciseIdentifier":"c:@M@ScanbotSDK@objc(cs)SBSDKUI2ScanCompletionOverlay","identifier":"doc:\/\/net.doo.ScanbotSDK\/documentation\/ScanbotSDK\/SBSDKUI2ScanCompletionOverlay","kind":"typeIdentifier","text":"SBSDKUI2ScanCompletionOverlay"},{"kind":"text","text":" *) "},{"kind":"internalParam","text":"successOverlay"},{"kind":"text","text":" "},{"kind":"identifier","text":"noDocumentDetectedAlertDialog:"},{"kind":"text","text":"("},{"preciseIdentifier":"c:@M@ScanbotSDK@objc(cs)SBSDKUI2ScanbotAlertDialog","identifier":"doc:\/\/net.doo.ScanbotSDK\/documentation\/ScanbotSDK\/SBSDKUI2ScanbotAlertDialog","kind":"typeIdentifier","text":"SBSDKUI2ScanbotAlertDialog"},{"kind":"text","text":" *) "},{"kind":"internalParam","text":"noDocumentDetectedAlertDialog"},{"kind":"text","text":" "},{"kind":"identifier","text":"cantProcessDocumentAlertDialog:"},{"kind":"text","text":"("},{"preciseIdentifier":"c:@M@ScanbotSDK@objc(cs)SBSDKUI2ScanbotAlertDialog","identifier":"doc:\/\/net.doo.ScanbotSDK\/documentation\/ScanbotSDK\/SBSDKUI2ScanbotAlertDialog","kind":"typeIdentifier","text":"SBSDKUI2ScanbotAlertDialog"},{"kind":"text","text":" *) "},{"kind":"internalParam","text":"cantProcessDocumentAlertDialog"},{"kind":"text","text":" "},{"kind":"identifier","text":"unsupportedDocumentAlertDialog:"},{"kind":"text","text":"("},{"preciseIdentifier":"c:@M@ScanbotSDK@objc(cs)SBSDKUI2ScanbotAlertDialog","identifier":"doc:\/\/net.doo.ScanbotSDK\/documentation\/ScanbotSDK\/SBSDKUI2ScanbotAlertDialog","kind":"typeIdentifier","text":"SBSDKUI2ScanbotAlertDialog"},{"kind":"text","text":" *) "},{"kind":"internalParam","text":"unsupportedDocumentAlertDialog"},{"kind":"text","text":" "},{"kind":"identifier","text":"scanningTooLongAlertDialog:"},{"kind":"text","text":"("},{"preciseIdentifier":"c:@M@ScanbotSDK@objc(cs)SBSDKUI2ScanbotAlertDialog","identifier":"doc:\/\/net.doo.ScanbotSDK\/documentation\/ScanbotSDK\/SBSDKUI2ScanbotAlertDialog","kind":"typeIdentifier","text":"SBSDKUI2ScanbotAlertDialog"},{"kind":"text","text":" *) "},{"kind":"internalParam","text":"scanningTooLongAlertDialog"},{"kind":"text","text":" "},{"kind":"identifier","text":"sound:"},{"kind":"text","text":"("},{"preciseIdentifier":"c:@M@ScanbotSDK@objc(cs)SBSDKUI2Sound","identifier":"doc:\/\/net.doo.ScanbotSDK\/documentation\/ScanbotSDK\/SBSDKUI2Sound","kind":"typeIdentifier","text":"SBSDKUI2Sound"},{"kind":"text","text":" *) "},{"kind":"internalParam","text":"sound"},{"kind":"text","text":" "},{"kind":"identifier","text":"vibration:"},{"kind":"text","text":"("},{"preciseIdentifier":"c:@M@ScanbotSDK@objc(cs)SBSDKUI2Vibration","identifier":"doc:\/\/net.doo.ScanbotSDK\/documentation\/ScanbotSDK\/SBSDKUI2Vibration","kind":"typeIdentifier","text":"SBSDKUI2Vibration"},{"kind":"text","text":" *) "},{"kind":"internalParam","text":"vibration"},{"kind":"text","text":" "},{"kind":"identifier","text":"keepScreenOn:"},{"kind":"text","text":"("},{"preciseIdentifier":"c:@T@BOOL","kind":"typeIdentifier","text":"BOOL"},{"kind":"text","text":") "},{"kind":"internalParam","text":"keepScreenOn"},{"kind":"text","text":";"}],"languages":["occ"]}],"kind":"declarations"}],"identifier":{"interfaceLanguage":"occ","url":"doc:\/\/net.doo.ScanbotSDK\/documentation\/ScanbotSDK\/SBSDKUI2DocumentDataExtractorScreenConfiguration\/initWithVersion:screen:localization:palette:backgroundColor:cameraConfiguration:cameraPermission:topUserGuidance:scanStatusUserGuidance:topBar:topBarOpenIntroScreenButton:introScreen:actionBar:viewFinder:scannerConfiguration:extractionProgress:noDocumentFoundTimeout:accumulationTimeout:successOverlay:noDocumentDetectedAlertDialog:cantProcessDocumentAlertDialog:unsupportedDocumentAlertDialog:scanningTooLongAlertDialog:sound:vibration:keepScreenOn:"},"kind":"symbol","variants":[{"traits":[{"interfaceLanguage":"occ"}],"paths":["\/documentation\/scanbotsdk\/sbsdkui2documentdataextractorscreenconfiguration\/initwithversion:screen:localization:palette:backgroundcolor:cameraconfiguration:camerapermission:topuserguidance:scanstatususerguidance:topbar:topbaropenintroscreenbutton:introscreen:actionbar:viewfinder:scannerconfiguration:extractionprogr-1f4af"]}],"metadata":{"externalID":"c:@M@ScanbotSDK@objc(cs)SBSDKUI2DocumentDataExtractorScreenConfiguration(im)initWithVersion:screen:localization:palette:backgroundColor:cameraConfiguration:cameraPermission:topUserGuidance:scanStatusUserGuidance:topBar:topBarOpenIntroScreenButton:introScreen:actionBar:viewFinder:scannerConfiguration:extractionProgress:noDocumentFoundTimeout:accumulationTimeout:successOverlay:noDocumentDetectedAlertDialog:cantProcessDocumentAlertDialog:unsupportedDocumentAlertDialog:scanningTooLongAlertDialog:sound:vibration:keepScreenOn:","roleHeading":"Instance Method","fragments":[{"kind":"text","text":"- "},{"kind":"identifier","text":"initWithVersion:screen:localization:palette:backgroundColor:cameraConfiguration:cameraPermission:topUserGuidance:scanStatusUserGuidance:topBar:topBarOpenIntroScreenButton:introScreen:actionBar:viewFinder:scannerConfiguration:extractionProgress:noDocumentFoundTimeout:accumulationTimeout:successOverlay:noDocumentDetectedAlertDialog:cantProcessDocumentAlertDialog:unsupportedDocumentAlertDialog:scanningTooLongAlertDialog:sound:vibration:keepScreenOn:"}],"symbolKind":"method","navigatorTitle":[{"text":"initWithVersion:screen:localization:palette:backgroundColor:cameraConfiguration:cameraPermission:topUserGuidance:scanStatusUserGuidance:topBar:topBarOpenIntroScreenButton:introScreen:actionBar:viewFinder:scannerConfiguration:extractionProgress:noDocumentFoundTimeout:accumulationTimeout:successOverlay:noDocumentDetectedAlertDialog:cantProcessDocumentAlertDialog:unsupportedDocumentAlertDialog:scanningTooLongAlertDialog:sound:vibration:keepScreenOn:","kind":"identifier"}],"title":"initWithVersion:screen:localization:palette:backgroundColor:cameraConfiguration:cameraPermission:topUserGuidance:scanStatusUserGuidance:topBar:topBarOpenIntroScreenButton:introScreen:actionBar:viewFinder:scannerConfiguration:extractionProgress:noDocumentFoundTimeout:accumulationTimeout:successOverlay:noDocumentDetectedAlertDialog:cantProcessDocumentAlertDialog:unsupportedDocumentAlertDialog:scanningTooLongAlertDialog:sound:vibration:keepScreenOn:","role":"symbol","modules":[{"name":"ScanbotSDK"}]},"references":{"doc://net.doo.ScanbotSDK/documentation/ScanbotSDK/SBSDKUI2UserGuidanceConfiguration":{"type":"topic","title":"SBSDKUI2UserGuidanceConfiguration","role":"symbol","kind":"symbol","abstract":[{"type":"text","text":"Configuration of the hint guiding users through the scanning process."}],"navigatorTitle":[{"kind":"identifier","text":"SBSDKUI2UserGuidanceConfiguration"}],"fragments":[{"kind":"keyword","text":"class"},{"kind":"text","text":" "},{"kind":"identifier","text":"SBSDKUI2UserGuidanceConfiguration"}],"url":"\/documentation\/scanbotsdk\/sbsdkui2userguidanceconfiguration","identifier":"doc:\/\/net.doo.ScanbotSDK\/documentation\/ScanbotSDK\/SBSDKUI2UserGuidanceConfiguration"},"doc://net.doo.ScanbotSDK/documentation/ScanbotSDK/SBSDKUI2DocumentDataExtractorGuidanceConfiguration":{"abstract":[{"type":"text","text":"Configuration of the hints guiding users through the document scanning process."}],"kind":"symbol","role":"symbol","fragments":[{"kind":"keyword","text":"class"},{"kind":"text","text":" "},{"kind":"identifier","text":"SBSDKUI2DocumentDataExtractorGuidanceConfiguration"}],"title":"SBSDKUI2DocumentDataExtractorGuidanceConfiguration","type":"topic","identifier":"doc:\/\/net.doo.ScanbotSDK\/documentation\/ScanbotSDK\/SBSDKUI2DocumentDataExtractorGuidanceConfiguration","navigatorTitle":[{"kind":"identifier","text":"SBSDKUI2DocumentDataExtractorGuidanceConfiguration"}],"url":"\/documentation\/scanbotsdk\/sbsdkui2documentdataextractorguidanceconfiguration"},"doc://net.doo.ScanbotSDK/documentation/ScanbotSDK/SBSDKUI2ScanCompletionOverlay":{"kind":"symbol","fragments":[{"text":"class","kind":"keyword"},{"text":" ","kind":"text"},{"text":"SBSDKUI2ScanCompletionOverlay","kind":"identifier"}],"navigatorTitle":[{"text":"SBSDKUI2ScanCompletionOverlay","kind":"identifier"}],"url":"\/documentation\/scanbotsdk\/sbsdkui2scancompletionoverlay","title":"SBSDKUI2ScanCompletionOverlay","identifier":"doc:\/\/net.doo.ScanbotSDK\/documentation\/ScanbotSDK\/SBSDKUI2ScanCompletionOverlay","role":"symbol","abstract":[{"text":"Configuration of the overlay to be shown after the successful scan.","type":"text"}],"type":"topic"},"doc://net.doo.ScanbotSDK/documentation/ScanbotSDK/SBSDKUI2CameraConfiguration":{"type":"topic","navigatorTitle":[{"kind":"identifier","text":"SBSDKUI2CameraConfiguration"}],"identifier":"doc:\/\/net.doo.ScanbotSDK\/documentation\/ScanbotSDK\/SBSDKUI2CameraConfiguration","kind":"symbol","role":"symbol","title":"SBSDKUI2CameraConfiguration","fragments":[{"kind":"keyword","text":"class"},{"kind":"text","text":" "},{"kind":"identifier","text":"SBSDKUI2CameraConfiguration"}],"url":"\/documentation\/scanbotsdk\/sbsdkui2cameraconfiguration","abstract":[{"type":"text","text":"Configuration of the camera settings to be used while scanning."}]},"doc://net.doo.ScanbotSDK/documentation/ScanbotSDK/SBSDKUI2ScanbotAlertDialog":{"type":"topic","role":"symbol","fragments":[{"kind":"keyword","text":"class"},{"kind":"text","text":" "},{"kind":"identifier","text":"SBSDKUI2ScanbotAlertDialog"}],"abstract":[{"text":"Configuration of the standard alert dialog.","type":"text"}],"navigatorTitle":[{"kind":"identifier","text":"SBSDKUI2ScanbotAlertDialog"}],"title":"SBSDKUI2ScanbotAlertDialog","url":"\/documentation\/scanbotsdk\/sbsdkui2scanbotalertdialog","kind":"symbol","identifier":"doc:\/\/net.doo.ScanbotSDK\/documentation\/ScanbotSDK\/SBSDKUI2ScanbotAlertDialog"},"doc://net.doo.ScanbotSDK/documentation/ScanbotSDK/SBSDKUI2TopBarConfiguration":{"identifier":"doc:\/\/net.doo.ScanbotSDK\/documentation\/ScanbotSDK\/SBSDKUI2TopBarConfiguration","role":"symbol","url":"\/documentation\/scanbotsdk\/sbsdkui2topbarconfiguration","title":"SBSDKUI2TopBarConfiguration","fragments":[{"kind":"keyword","text":"class"},{"kind":"text","text":" "},{"kind":"identifier","text":"SBSDKUI2TopBarConfiguration"}],"type":"topic","kind":"symbol","navigatorTitle":[{"kind":"identifier","text":"SBSDKUI2TopBarConfiguration"}],"abstract":[{"type":"text","text":"Configuration of the top bar’s appearance."}]},"doc://net.doo.ScanbotSDK/documentation/ScanbotSDK/SBSDKDocumentDataExtractorConfiguration":{"identifier":"doc:\/\/net.doo.ScanbotSDK\/documentation\/ScanbotSDK\/SBSDKDocumentDataExtractorConfiguration","title":"SBSDKDocumentDataExtractorConfiguration","kind":"symbol","fragments":[{"text":"class","kind":"keyword"},{"text":" ","kind":"text"},{"text":"SBSDKDocumentDataExtractorConfiguration","kind":"identifier"}],"type":"topic","role":"symbol","abstract":[{"text":"Configuration for the document data extractor.","type":"text"}],"navigatorTitle":[{"text":"SBSDKDocumentDataExtractorConfiguration","kind":"identifier"}],"url":"\/documentation\/scanbotsdk\/sbsdkdocumentdataextractorconfiguration"},"doc://net.doo.ScanbotSDK/documentation/ScanbotSDK/SBSDKUI2CameraPermissionScreen":{"abstract":[{"type":"text","text":"Configuration of the camera permission request view."}],"url":"\/documentation\/scanbotsdk\/sbsdkui2camerapermissionscreen","type":"topic","navigatorTitle":[{"kind":"identifier","text":"SBSDKUI2CameraPermissionScreen"}],"fragments":[{"kind":"keyword","text":"class"},{"kind":"text","text":" "},{"kind":"identifier","text":"SBSDKUI2CameraPermissionScreen"}],"kind":"symbol","identifier":"doc:\/\/net.doo.ScanbotSDK\/documentation\/ScanbotSDK\/SBSDKUI2CameraPermissionScreen","title":"SBSDKUI2CameraPermissionScreen","role":"symbol"},"doc://net.doo.ScanbotSDK/documentation/ScanbotSDK/SBSDKUI2Sound":{"fragments":[{"text":"class","kind":"keyword"},{"text":" ","kind":"text"},{"text":"SBSDKUI2Sound","kind":"identifier"}],"role":"symbol","type":"topic","kind":"symbol","abstract":[{"text":"Configuration for the sound.","type":"text"}],"navigatorTitle":[{"text":"SBSDKUI2Sound","kind":"identifier"}],"url":"\/documentation\/scanbotsdk\/sbsdkui2sound","identifier":"doc:\/\/net.doo.ScanbotSDK\/documentation\/ScanbotSDK\/SBSDKUI2Sound","title":"SBSDKUI2Sound"},"doc://net.doo.ScanbotSDK/documentation/ScanbotSDK/SBSDKUI2DocumentDataExtractorScreenConfiguration":{"identifier":"doc:\/\/net.doo.ScanbotSDK\/documentation\/ScanbotSDK\/SBSDKUI2DocumentDataExtractorScreenConfiguration","url":"\/documentation\/scanbotsdk\/sbsdkui2documentdataextractorscreenconfiguration","kind":"symbol","type":"topic","title":"SBSDKUI2DocumentDataExtractorScreenConfiguration","navigatorTitle":[{"kind":"identifier","text":"SBSDKUI2DocumentDataExtractorScreenConfiguration"}],"abstract":[{"text":"Configuration of the screen for extracting data from ID documents.","type":"text"}],"role":"symbol","fragments":[{"kind":"keyword","text":"class"},{"kind":"text","text":" "},{"kind":"identifier","text":"SBSDKUI2DocumentDataExtractorScreenConfiguration"}]},"doc://net.doo.ScanbotSDK/documentation/ScanbotSDK/SBSDKUI2DocumentDataExtractorScreenConfiguration/initWithVersion:screen:localization:palette:backgroundColor:cameraConfiguration:cameraPermission:topUserGuidance:scanStatusUserGuidance:topBar:topBarOpenIntroScreenButton:introScreen:actionBar:viewFinder:scannerConfiguration:extractionProgress:noDocumentFoundTimeout:accumulationTimeout:successOverlay:noDocumentDetectedAlertDialog:cantProcessDocumentAlertDialog:unsupportedDocumentAlertDialog:scanningTooLongAlertDialog:sound:vibration:keepScreenOn:":{"fragments":[{"kind":"text","text":"- "},{"kind":"identifier","text":"initWithVersion:screen:localization:palette:backgroundColor:cameraConfiguration:cameraPermission:topUserGuidance:scanStatusUserGuidance:topBar:topBarOpenIntroScreenButton:introScreen:actionBar:viewFinder:scannerConfiguration:extractionProgress:noDocumentFoundTimeout:accumulationTimeout:successOverlay:noDocumentDetectedAlertDialog:cantProcessDocumentAlertDialog:unsupportedDocumentAlertDialog:scanningTooLongAlertDialog:sound:vibration:keepScreenOn:"}],"navigatorTitle":[{"kind":"identifier","text":"initWithVersion:screen:localization:palette:backgroundColor:cameraConfiguration:cameraPermission:topUserGuidance:scanStatusUserGuidance:topBar:topBarOpenIntroScreenButton:introScreen:actionBar:viewFinder:scannerConfiguration:extractionProgress:noDocumentFoundTimeout:accumulationTimeout:successOverlay:noDocumentDetectedAlertDialog:cantProcessDocumentAlertDialog:unsupportedDocumentAlertDialog:scanningTooLongAlertDialog:sound:vibration:keepScreenOn:"}],"type":"topic","kind":"symbol","title":"initWithVersion:screen:localization:palette:backgroundColor:cameraConfiguration:cameraPermission:topUserGuidance:scanStatusUserGuidance:topBar:topBarOpenIntroScreenButton:introScreen:actionBar:viewFinder:scannerConfiguration:extractionProgress:noDocumentFoundTimeout:accumulationTimeout:successOverlay:noDocumentDetectedAlertDialog:cantProcessDocumentAlertDialog:unsupportedDocumentAlertDialog:scanningTooLongAlertDialog:sound:vibration:keepScreenOn:","abstract":[],"identifier":"doc:\/\/net.doo.ScanbotSDK\/documentation\/ScanbotSDK\/SBSDKUI2DocumentDataExtractorScreenConfiguration\/initWithVersion:screen:localization:palette:backgroundColor:cameraConfiguration:cameraPermission:topUserGuidance:scanStatusUserGuidance:topBar:topBarOpenIntroScreenButton:introScreen:actionBar:viewFinder:scannerConfiguration:extractionProgress:noDocumentFoundTimeout:accumulationTimeout:successOverlay:noDocumentDetectedAlertDialog:cantProcessDocumentAlertDialog:unsupportedDocumentAlertDialog:scanningTooLongAlertDialog:sound:vibration:keepScreenOn:","url":"\/documentation\/scanbotsdk\/sbsdkui2documentdataextractorscreenconfiguration\/initwithversion:screen:localization:palette:backgroundcolor:cameraconfiguration:camerapermission:topuserguidance:scanstatususerguidance:topbar:topbaropenintroscreenbutton:introscreen:actionbar:viewfinder:scannerconfiguration:extractionprogr-1f4af","role":"symbol"},"doc://net.doo.ScanbotSDK/documentation/ScanbotSDK/SBSDKUI2Palette":{"navigatorTitle":[{"text":"SBSDKUI2Palette","kind":"identifier"}],"kind":"symbol","type":"topic","url":"\/documentation\/scanbotsdk\/sbsdkui2palette","title":"SBSDKUI2Palette","abstract":[{"type":"text","text":"Value palette describing the colors of the scanner screens."}],"identifier":"doc:\/\/net.doo.ScanbotSDK\/documentation\/ScanbotSDK\/SBSDKUI2Palette","role":"symbol","fragments":[{"text":"class","kind":"keyword"},{"text":" ","kind":"text"},{"text":"SBSDKUI2Palette","kind":"identifier"}]},"doc://net.doo.ScanbotSDK/documentation/ScanbotSDK/SBSDKUI2PermanentViewFinderConfiguration":{"type":"topic","role":"symbol","url":"\/documentation\/scanbotsdk\/sbsdkui2permanentviewfinderconfiguration","title":"SBSDKUI2PermanentViewFinderConfiguration","abstract":[{"text":"Configuration of the scanning interface’s viewfinder, which is always visible to guide the user.","type":"text"}],"fragments":[{"text":"class","kind":"keyword"},{"text":" ","kind":"text"},{"text":"SBSDKUI2PermanentViewFinderConfiguration","kind":"identifier"}],"identifier":"doc:\/\/net.doo.ScanbotSDK\/documentation\/ScanbotSDK\/SBSDKUI2PermanentViewFinderConfiguration","navigatorTitle":[{"text":"SBSDKUI2PermanentViewFinderConfiguration","kind":"identifier"}],"kind":"symbol"},"doc://net.doo.ScanbotSDK/documentation/ScanbotSDK/SBSDKUI2Color":{"identifier":"doc:\/\/net.doo.ScanbotSDK\/documentation\/ScanbotSDK\/SBSDKUI2Color","fragments":[{"text":"class","kind":"keyword"},{"text":" ","kind":"text"},{"text":"SBSDKUI2Color","kind":"identifier"}],"navigatorTitle":[{"text":"SBSDKUI2Color","kind":"identifier"}],"url":"\/documentation\/scanbotsdk\/sbsdkui2color","type":"topic","role":"symbol","kind":"symbol","title":"SBSDKUI2Color","abstract":[]},"doc://net.doo.ScanbotSDK/documentation/ScanbotSDK/SBSDKUI2IconButton":{"title":"SBSDKUI2IconButton","abstract":[{"text":"Configuration of the icon appearance on a button.","type":"text"}],"url":"\/documentation\/scanbotsdk\/sbsdkui2iconbutton","identifier":"doc:\/\/net.doo.ScanbotSDK\/documentation\/ScanbotSDK\/SBSDKUI2IconButton","kind":"symbol","role":"symbol","fragments":[{"text":"class","kind":"keyword"},{"text":" ","kind":"text"},{"text":"SBSDKUI2IconButton","kind":"identifier"}],"type":"topic","navigatorTitle":[{"text":"SBSDKUI2IconButton","kind":"identifier"}]},"doc://net.doo.ScanbotSDK/documentation/ScanbotSDK/SBSDKUI2Vibration":{"url":"\/documentation\/scanbotsdk\/sbsdkui2vibration","abstract":[{"type":"text","text":"Configure the vibration."}],"fragments":[{"kind":"keyword","text":"class"},{"kind":"text","text":" "},{"kind":"identifier","text":"SBSDKUI2Vibration"}],"navigatorTitle":[{"kind":"identifier","text":"SBSDKUI2Vibration"}],"title":"SBSDKUI2Vibration","kind":"symbol","identifier":"doc:\/\/net.doo.ScanbotSDK\/documentation\/ScanbotSDK\/SBSDKUI2Vibration","role":"symbol","type":"topic"},"doc://net.doo.ScanbotSDK/documentation/ScanbotSDK":{"title":"ScanbotSDK","abstract":[{"type":"text","text":"Version: 8.0.0"}],"identifier":"doc:\/\/net.doo.ScanbotSDK\/documentation\/ScanbotSDK","role":"collection","kind":"symbol","type":"topic","url":"\/documentation\/scanbotsdk"},"doc://net.doo.ScanbotSDK/documentation/ScanbotSDK/SBSDKUI2DocumentDataExtractorIntroScreenConfiguration":{"kind":"symbol","type":"topic","role":"symbol","url":"\/documentation\/scanbotsdk\/sbsdkui2documentdataextractorintroscreenconfiguration","abstract":[{"type":"text","text":"Configuration of the introduction screen for the document data extractor."}],"identifier":"doc:\/\/net.doo.ScanbotSDK\/documentation\/ScanbotSDK\/SBSDKUI2DocumentDataExtractorIntroScreenConfiguration","fragments":[{"kind":"keyword","text":"class"},{"kind":"text","text":" "},{"kind":"identifier","text":"SBSDKUI2DocumentDataExtractorIntroScreenConfiguration"}],"navigatorTitle":[{"kind":"identifier","text":"SBSDKUI2DocumentDataExtractorIntroScreenConfiguration"}],"title":"SBSDKUI2DocumentDataExtractorIntroScreenConfiguration"},"doc://net.doo.ScanbotSDK/documentation/ScanbotSDK/SBSDKUI2ActionBarConfiguration":{"fragments":[{"kind":"keyword","text":"class"},{"kind":"text","text":" "},{"kind":"identifier","text":"SBSDKUI2ActionBarConfiguration"}],"title":"SBSDKUI2ActionBarConfiguration","type":"topic","identifier":"doc:\/\/net.doo.ScanbotSDK\/documentation\/ScanbotSDK\/SBSDKUI2ActionBarConfiguration","navigatorTitle":[{"kind":"identifier","text":"SBSDKUI2ActionBarConfiguration"}],"kind":"symbol","role":"symbol","url":"\/documentation\/scanbotsdk\/sbsdkui2actionbarconfiguration","abstract":[{"type":"text","text":"Configuration of the buttons available in the action bar."}]},"doc://net.doo.ScanbotSDK/documentation/ScanbotSDK/SBSDKUI2DocumentDataExtractorScreenTextLocalization":{"navigatorTitle":[{"text":"SBSDKUI2DocumentDataExtractorScreenTextLocalization","kind":"identifier"}],"identifier":"doc:\/\/net.doo.ScanbotSDK\/documentation\/ScanbotSDK\/SBSDKUI2DocumentDataExtractorScreenTextLocalization","kind":"symbol","title":"SBSDKUI2DocumentDataExtractorScreenTextLocalization","type":"topic","role":"symbol","abstract":[{"type":"text","text":"Configuration of the all strings for document data extractor screen."}],"url":"\/documentation\/scanbotsdk\/sbsdkui2documentdataextractorscreentextlocalization","fragments":[{"text":"class","kind":"keyword"},{"text":" ","kind":"text"},{"text":"SBSDKUI2DocumentDataExtractorScreenTextLocalization","kind":"identifier"}]},"doc://net.doo.ScanbotSDK/documentation/ScanbotSDK/SBSDKUI2DocumentDataExtractionProgressConfiguration":{"url":"\/documentation\/scanbotsdk\/sbsdkui2documentdataextractionprogressconfiguration","navigatorTitle":[{"kind":"identifier","text":"SBSDKUI2DocumentDataExtractionProgressConfiguration"}],"role":"symbol","type":"topic","title":"SBSDKUI2DocumentDataExtractionProgressConfiguration","abstract":[{"text":"Configuration of visualization of the scanning progress - indeterminate progress.","type":"text"}],"kind":"symbol","fragments":[{"kind":"keyword","text":"class"},{"kind":"text","text":" "},{"kind":"identifier","text":"SBSDKUI2DocumentDataExtractionProgressConfiguration"}],"identifier":"doc:\/\/net.doo.ScanbotSDK\/documentation\/ScanbotSDK\/SBSDKUI2DocumentDataExtractionProgressConfiguration"}},"variantOverrides":[{"traits":[{"interfaceLanguage":"occ"}],"patch":[{"path":"\/references\/doc:~1~1net.doo.ScanbotSDK~1documentation~1ScanbotSDK~1SBSDKUI2UserGuidanceConfiguration\/title","value":"SBSDKUI2UserGuidanceConfiguration","op":"replace"},{"path":"\/references\/doc:~1~1net.doo.ScanbotSDK~1documentation~1ScanbotSDK~1SBSDKUI2UserGuidanceConfiguration\/fragments","value":[{"text":"SBSDKUI2UserGuidanceConfiguration","kind":"identifier"}],"op":"replace"},{"path":"\/references\/doc:~1~1net.doo.ScanbotSDK~1documentation~1ScanbotSDK~1SBSDKUI2UserGuidanceConfiguration\/navigatorTitle","value":[{"kind":"identifier","text":"SBSDKUI2UserGuidanceConfiguration"}],"op":"replace"},{"path":"\/references\/doc:~1~1net.doo.ScanbotSDK~1documentation~1ScanbotSDK~1SBSDKUI2DocumentDataExtractorGuidanceConfiguration\/title","value":"SBSDKUI2DocumentDataExtractorGuidanceConfiguration","op":"replace"},{"path":"\/references\/doc:~1~1net.doo.ScanbotSDK~1documentation~1ScanbotSDK~1SBSDKUI2DocumentDataExtractorGuidanceConfiguration\/fragments","value":[{"kind":"identifier","text":"SBSDKUI2DocumentDataExtractorGuidanceConfiguration"}],"op":"replace"},{"path":"\/references\/doc:~1~1net.doo.ScanbotSDK~1documentation~1ScanbotSDK~1SBSDKUI2DocumentDataExtractorGuidanceConfiguration\/navigatorTitle","value":[{"kind":"identifier","text":"SBSDKUI2DocumentDataExtractorGuidanceConfiguration"}],"op":"replace"},{"path":"\/references\/doc:~1~1net.doo.ScanbotSDK~1documentation~1ScanbotSDK~1SBSDKUI2ScanCompletionOverlay\/title","value":"SBSDKUI2ScanCompletionOverlay","op":"replace"},{"path":"\/references\/doc:~1~1net.doo.ScanbotSDK~1documentation~1ScanbotSDK~1SBSDKUI2ScanCompletionOverlay\/fragments","value":[{"text":"SBSDKUI2ScanCompletionOverlay","kind":"identifier"}],"op":"replace"},{"path":"\/references\/doc:~1~1net.doo.ScanbotSDK~1documentation~1ScanbotSDK~1SBSDKUI2ScanCompletionOverlay\/navigatorTitle","value":[{"text":"SBSDKUI2ScanCompletionOverlay","kind":"identifier"}],"op":"replace"},{"path":"\/references\/doc:~1~1net.doo.ScanbotSDK~1documentation~1ScanbotSDK~1SBSDKUI2CameraConfiguration\/title","value":"SBSDKUI2CameraConfiguration","op":"replace"},{"path":"\/references\/doc:~1~1net.doo.ScanbotSDK~1documentation~1ScanbotSDK~1SBSDKUI2CameraConfiguration\/fragments","value":[{"kind":"identifier","text":"SBSDKUI2CameraConfiguration"}],"op":"replace"},{"path":"\/references\/doc:~1~1net.doo.ScanbotSDK~1documentation~1ScanbotSDK~1SBSDKUI2CameraConfiguration\/navigatorTitle","value":[{"text":"SBSDKUI2CameraConfiguration","kind":"identifier"}],"op":"replace"},{"path":"\/references\/doc:~1~1net.doo.ScanbotSDK~1documentation~1ScanbotSDK~1SBSDKUI2ScanbotAlertDialog\/title","value":"SBSDKUI2ScanbotAlertDialog","op":"replace"},{"path":"\/references\/doc:~1~1net.doo.ScanbotSDK~1documentation~1ScanbotSDK~1SBSDKUI2ScanbotAlertDialog\/fragments","value":[{"kind":"identifier","text":"SBSDKUI2ScanbotAlertDialog"}],"op":"replace"},{"path":"\/references\/doc:~1~1net.doo.ScanbotSDK~1documentation~1ScanbotSDK~1SBSDKUI2ScanbotAlertDialog\/navigatorTitle","value":[{"text":"SBSDKUI2ScanbotAlertDialog","kind":"identifier"}],"op":"replace"},{"path":"\/references\/doc:~1~1net.doo.ScanbotSDK~1documentation~1ScanbotSDK~1SBSDKUI2TopBarConfiguration\/title","value":"SBSDKUI2TopBarConfiguration","op":"replace"},{"path":"\/references\/doc:~1~1net.doo.ScanbotSDK~1documentation~1ScanbotSDK~1SBSDKUI2TopBarConfiguration\/fragments","value":[{"text":"SBSDKUI2TopBarConfiguration","kind":"identifier"}],"op":"replace"},{"path":"\/references\/doc:~1~1net.doo.ScanbotSDK~1documentation~1ScanbotSDK~1SBSDKUI2TopBarConfiguration\/navigatorTitle","value":[{"kind":"identifier","text":"SBSDKUI2TopBarConfiguration"}],"op":"replace"},{"path":"\/references\/doc:~1~1net.doo.ScanbotSDK~1documentation~1ScanbotSDK~1SBSDKDocumentDataExtractorConfiguration\/title","value":"SBSDKDocumentDataExtractorConfiguration","op":"replace"},{"path":"\/references\/doc:~1~1net.doo.ScanbotSDK~1documentation~1ScanbotSDK~1SBSDKDocumentDataExtractorConfiguration\/fragments","value":[{"text":"SBSDKDocumentDataExtractorConfiguration","kind":"identifier"}],"op":"replace"},{"path":"\/references\/doc:~1~1net.doo.ScanbotSDK~1documentation~1ScanbotSDK~1SBSDKDocumentDataExtractorConfiguration\/navigatorTitle","value":[{"kind":"identifier","text":"SBSDKDocumentDataExtractorConfiguration"}],"op":"replace"},{"path":"\/references\/doc:~1~1net.doo.ScanbotSDK~1documentation~1ScanbotSDK~1SBSDKUI2CameraPermissionScreen\/title","value":"SBSDKUI2CameraPermissionScreen","op":"replace"},{"path":"\/references\/doc:~1~1net.doo.ScanbotSDK~1documentation~1ScanbotSDK~1SBSDKUI2CameraPermissionScreen\/fragments","value":[{"kind":"identifier","text":"SBSDKUI2CameraPermissionScreen"}],"op":"replace"},{"path":"\/references\/doc:~1~1net.doo.ScanbotSDK~1documentation~1ScanbotSDK~1SBSDKUI2CameraPermissionScreen\/navigatorTitle","value":[{"text":"SBSDKUI2CameraPermissionScreen","kind":"identifier"}],"op":"replace"},{"path":"\/references\/doc:~1~1net.doo.ScanbotSDK~1documentation~1ScanbotSDK~1SBSDKUI2Sound\/title","value":"SBSDKUI2Sound","op":"replace"},{"path":"\/references\/doc:~1~1net.doo.ScanbotSDK~1documentation~1ScanbotSDK~1SBSDKUI2Sound\/fragments","value":[{"text":"SBSDKUI2Sound","kind":"identifier"}],"op":"replace"},{"path":"\/references\/doc:~1~1net.doo.ScanbotSDK~1documentation~1ScanbotSDK~1SBSDKUI2Sound\/navigatorTitle","value":[{"kind":"identifier","text":"SBSDKUI2Sound"}],"op":"replace"},{"path":"\/references\/doc:~1~1net.doo.ScanbotSDK~1documentation~1ScanbotSDK~1SBSDKUI2DocumentDataExtractorScreenConfiguration\/title","value":"SBSDKUI2DocumentDataExtractorScreenConfiguration","op":"replace"},{"path":"\/references\/doc:~1~1net.doo.ScanbotSDK~1documentation~1ScanbotSDK~1SBSDKUI2DocumentDataExtractorScreenConfiguration\/fragments","value":[{"kind":"identifier","text":"SBSDKUI2DocumentDataExtractorScreenConfiguration"}],"op":"replace"},{"path":"\/references\/doc:~1~1net.doo.ScanbotSDK~1documentation~1ScanbotSDK~1SBSDKUI2DocumentDataExtractorScreenConfiguration\/navigatorTitle","value":[{"text":"SBSDKUI2DocumentDataExtractorScreenConfiguration","kind":"identifier"}],"op":"replace"},{"path":"\/references\/doc:~1~1net.doo.ScanbotSDK~1documentation~1ScanbotSDK~1SBSDKUI2Palette\/title","value":"SBSDKUI2Palette","op":"replace"},{"path":"\/references\/doc:~1~1net.doo.ScanbotSDK~1documentation~1ScanbotSDK~1SBSDKUI2Palette\/fragments","value":[{"kind":"identifier","text":"SBSDKUI2Palette"}],"op":"replace"},{"path":"\/references\/doc:~1~1net.doo.ScanbotSDK~1documentation~1ScanbotSDK~1SBSDKUI2Palette\/navigatorTitle","value":[{"kind":"identifier","text":"SBSDKUI2Palette"}],"op":"replace"},{"path":"\/references\/doc:~1~1net.doo.ScanbotSDK~1documentation~1ScanbotSDK~1SBSDKUI2PermanentViewFinderConfiguration\/title","value":"SBSDKUI2PermanentViewFinderConfiguration","op":"replace"},{"path":"\/references\/doc:~1~1net.doo.ScanbotSDK~1documentation~1ScanbotSDK~1SBSDKUI2PermanentViewFinderConfiguration\/fragments","value":[{"text":"SBSDKUI2PermanentViewFinderConfiguration","kind":"identifier"}],"op":"replace"},{"path":"\/references\/doc:~1~1net.doo.ScanbotSDK~1documentation~1ScanbotSDK~1SBSDKUI2PermanentViewFinderConfiguration\/navigatorTitle","value":[{"text":"SBSDKUI2PermanentViewFinderConfiguration","kind":"identifier"}],"op":"replace"},{"path":"\/references\/doc:~1~1net.doo.ScanbotSDK~1documentation~1ScanbotSDK~1SBSDKUI2Color\/title","value":"SBSDKUI2Color","op":"replace"},{"path":"\/references\/doc:~1~1net.doo.ScanbotSDK~1documentation~1ScanbotSDK~1SBSDKUI2Color\/fragments","value":[{"text":"SBSDKUI2Color","kind":"identifier"}],"op":"replace"},{"path":"\/references\/doc:~1~1net.doo.ScanbotSDK~1documentation~1ScanbotSDK~1SBSDKUI2Color\/navigatorTitle","value":[{"text":"SBSDKUI2Color","kind":"identifier"}],"op":"replace"},{"path":"\/references\/doc:~1~1net.doo.ScanbotSDK~1documentation~1ScanbotSDK~1SBSDKUI2IconButton\/title","value":"SBSDKUI2IconButton","op":"replace"},{"path":"\/references\/doc:~1~1net.doo.ScanbotSDK~1documentation~1ScanbotSDK~1SBSDKUI2IconButton\/fragments","value":[{"text":"SBSDKUI2IconButton","kind":"identifier"}],"op":"replace"},{"path":"\/references\/doc:~1~1net.doo.ScanbotSDK~1documentation~1ScanbotSDK~1SBSDKUI2IconButton\/navigatorTitle","value":[{"kind":"identifier","text":"SBSDKUI2IconButton"}],"op":"replace"},{"path":"\/references\/doc:~1~1net.doo.ScanbotSDK~1documentation~1ScanbotSDK~1SBSDKUI2Vibration\/title","value":"SBSDKUI2Vibration","op":"replace"},{"path":"\/references\/doc:~1~1net.doo.ScanbotSDK~1documentation~1ScanbotSDK~1SBSDKUI2Vibration\/fragments","value":[{"kind":"identifier","text":"SBSDKUI2Vibration"}],"op":"replace"},{"path":"\/references\/doc:~1~1net.doo.ScanbotSDK~1documentation~1ScanbotSDK~1SBSDKUI2Vibration\/navigatorTitle","value":[{"text":"SBSDKUI2Vibration","kind":"identifier"}],"op":"replace"},{"path":"\/references\/doc:~1~1net.doo.ScanbotSDK~1documentation~1ScanbotSDK~1SBSDKUI2DocumentDataExtractorIntroScreenConfiguration\/title","value":"SBSDKUI2DocumentDataExtractorIntroScreenConfiguration","op":"replace"},{"path":"\/references\/doc:~1~1net.doo.ScanbotSDK~1documentation~1ScanbotSDK~1SBSDKUI2DocumentDataExtractorIntroScreenConfiguration\/fragments","value":[{"text":"SBSDKUI2DocumentDataExtractorIntroScreenConfiguration","kind":"identifier"}],"op":"replace"},{"path":"\/references\/doc:~1~1net.doo.ScanbotSDK~1documentation~1ScanbotSDK~1SBSDKUI2DocumentDataExtractorIntroScreenConfiguration\/navigatorTitle","value":[{"kind":"identifier","text":"SBSDKUI2DocumentDataExtractorIntroScreenConfiguration"}],"op":"replace"},{"path":"\/references\/doc:~1~1net.doo.ScanbotSDK~1documentation~1ScanbotSDK~1SBSDKUI2ActionBarConfiguration\/title","value":"SBSDKUI2ActionBarConfiguration","op":"replace"},{"path":"\/references\/doc:~1~1net.doo.ScanbotSDK~1documentation~1ScanbotSDK~1SBSDKUI2ActionBarConfiguration\/fragments","value":[{"text":"SBSDKUI2ActionBarConfiguration","kind":"identifier"}],"op":"replace"},{"path":"\/references\/doc:~1~1net.doo.ScanbotSDK~1documentation~1ScanbotSDK~1SBSDKUI2ActionBarConfiguration\/navigatorTitle","value":[{"text":"SBSDKUI2ActionBarConfiguration","kind":"identifier"}],"op":"replace"},{"path":"\/references\/doc:~1~1net.doo.ScanbotSDK~1documentation~1ScanbotSDK~1SBSDKUI2DocumentDataExtractorScreenTextLocalization\/title","value":"SBSDKUI2DocumentDataExtractorScreenTextLocalization","op":"replace"},{"path":"\/references\/doc:~1~1net.doo.ScanbotSDK~1documentation~1ScanbotSDK~1SBSDKUI2DocumentDataExtractorScreenTextLocalization\/fragments","value":[{"kind":"identifier","text":"SBSDKUI2DocumentDataExtractorScreenTextLocalization"}],"op":"replace"},{"path":"\/references\/doc:~1~1net.doo.ScanbotSDK~1documentation~1ScanbotSDK~1SBSDKUI2DocumentDataExtractorScreenTextLocalization\/navigatorTitle","value":[{"text":"SBSDKUI2DocumentDataExtractorScreenTextLocalization","kind":"identifier"}],"op":"replace"},{"path":"\/references\/doc:~1~1net.doo.ScanbotSDK~1documentation~1ScanbotSDK~1SBSDKUI2DocumentDataExtractionProgressConfiguration\/title","value":"SBSDKUI2DocumentDataExtractionProgressConfiguration","op":"replace"},{"path":"\/references\/doc:~1~1net.doo.ScanbotSDK~1documentation~1ScanbotSDK~1SBSDKUI2DocumentDataExtractionProgressConfiguration\/fragments","value":[{"text":"SBSDKUI2DocumentDataExtractionProgressConfiguration","kind":"identifier"}],"op":"replace"},{"path":"\/references\/doc:~1~1net.doo.ScanbotSDK~1documentation~1ScanbotSDK~1SBSDKUI2DocumentDataExtractionProgressConfiguration\/navigatorTitle","value":[{"kind":"identifier","text":"SBSDKUI2DocumentDataExtractionProgressConfiguration"}],"op":"replace"}]}]}