{"primaryContentSections":[{"kind":"declarations","declarations":[{"languages":["occ"],"tokens":[{"kind":"text","text":"- ("},{"kind":"typeIdentifier","preciseIdentifier":"c:*Qo","text":"id"},{"kind":"text","text":") "},{"kind":"identifier","text":"initWithSbColorPrimary:"},{"kind":"text","text":"("},{"identifier":"doc:\/\/net.doo.ScanbotBarcodeScannerSDK\/documentation\/ScanbotBarcodeScannerSDK\/SBSDKUI2Color","kind":"typeIdentifier","preciseIdentifier":"c:@M@ScanbotBarcodeScannerSDK@objc(cs)SBSDKUI2Color","text":"SBSDKUI2Color"},{"kind":"text","text":" *) "},{"kind":"internalParam","text":"sbColorPrimary"},{"kind":"text","text":" "},{"kind":"identifier","text":"sbColorPrimaryDisabled:"},{"kind":"text","text":"("},{"identifier":"doc:\/\/net.doo.ScanbotBarcodeScannerSDK\/documentation\/ScanbotBarcodeScannerSDK\/SBSDKUI2Color","kind":"typeIdentifier","preciseIdentifier":"c:@M@ScanbotBarcodeScannerSDK@objc(cs)SBSDKUI2Color","text":"SBSDKUI2Color"},{"kind":"text","text":" *) "},{"kind":"internalParam","text":"sbColorPrimaryDisabled"},{"kind":"text","text":" "},{"kind":"identifier","text":"sbColorNegative:"},{"kind":"text","text":"("},{"identifier":"doc:\/\/net.doo.ScanbotBarcodeScannerSDK\/documentation\/ScanbotBarcodeScannerSDK\/SBSDKUI2Color","kind":"typeIdentifier","preciseIdentifier":"c:@M@ScanbotBarcodeScannerSDK@objc(cs)SBSDKUI2Color","text":"SBSDKUI2Color"},{"kind":"text","text":" *) "},{"kind":"internalParam","text":"sbColorNegative"},{"kind":"text","text":" "},{"kind":"identifier","text":"sbColorPositive:"},{"kind":"text","text":"("},{"identifier":"doc:\/\/net.doo.ScanbotBarcodeScannerSDK\/documentation\/ScanbotBarcodeScannerSDK\/SBSDKUI2Color","kind":"typeIdentifier","preciseIdentifier":"c:@M@ScanbotBarcodeScannerSDK@objc(cs)SBSDKUI2Color","text":"SBSDKUI2Color"},{"kind":"text","text":" *) "},{"kind":"internalParam","text":"sbColorPositive"},{"kind":"text","text":" "},{"kind":"identifier","text":"sbColorWarning:"},{"kind":"text","text":"("},{"identifier":"doc:\/\/net.doo.ScanbotBarcodeScannerSDK\/documentation\/ScanbotBarcodeScannerSDK\/SBSDKUI2Color","kind":"typeIdentifier","preciseIdentifier":"c:@M@ScanbotBarcodeScannerSDK@objc(cs)SBSDKUI2Color","text":"SBSDKUI2Color"},{"kind":"text","text":" *) "},{"kind":"internalParam","text":"sbColorWarning"},{"kind":"text","text":" "},{"kind":"identifier","text":"sbColorSecondary:"},{"kind":"text","text":"("},{"identifier":"doc:\/\/net.doo.ScanbotBarcodeScannerSDK\/documentation\/ScanbotBarcodeScannerSDK\/SBSDKUI2Color","kind":"typeIdentifier","preciseIdentifier":"c:@M@ScanbotBarcodeScannerSDK@objc(cs)SBSDKUI2Color","text":"SBSDKUI2Color"},{"kind":"text","text":" *) "},{"kind":"internalParam","text":"sbColorSecondary"},{"kind":"text","text":" "},{"kind":"identifier","text":"sbColorSecondaryDisabled:"},{"kind":"text","text":"("},{"identifier":"doc:\/\/net.doo.ScanbotBarcodeScannerSDK\/documentation\/ScanbotBarcodeScannerSDK\/SBSDKUI2Color","kind":"typeIdentifier","preciseIdentifier":"c:@M@ScanbotBarcodeScannerSDK@objc(cs)SBSDKUI2Color","text":"SBSDKUI2Color"},{"kind":"text","text":" *) "},{"kind":"internalParam","text":"sbColorSecondaryDisabled"},{"kind":"text","text":" "},{"kind":"identifier","text":"sbColorOnPrimary:"},{"kind":"text","text":"("},{"identifier":"doc:\/\/net.doo.ScanbotBarcodeScannerSDK\/documentation\/ScanbotBarcodeScannerSDK\/SBSDKUI2Color","kind":"typeIdentifier","preciseIdentifier":"c:@M@ScanbotBarcodeScannerSDK@objc(cs)SBSDKUI2Color","text":"SBSDKUI2Color"},{"kind":"text","text":" *) "},{"kind":"internalParam","text":"sbColorOnPrimary"},{"kind":"text","text":" "},{"kind":"identifier","text":"sbColorOnSecondary:"},{"kind":"text","text":"("},{"identifier":"doc:\/\/net.doo.ScanbotBarcodeScannerSDK\/documentation\/ScanbotBarcodeScannerSDK\/SBSDKUI2Color","kind":"typeIdentifier","preciseIdentifier":"c:@M@ScanbotBarcodeScannerSDK@objc(cs)SBSDKUI2Color","text":"SBSDKUI2Color"},{"kind":"text","text":" *) "},{"kind":"internalParam","text":"sbColorOnSecondary"},{"kind":"text","text":" "},{"kind":"identifier","text":"sbColorSurface:"},{"kind":"text","text":"("},{"identifier":"doc:\/\/net.doo.ScanbotBarcodeScannerSDK\/documentation\/ScanbotBarcodeScannerSDK\/SBSDKUI2Color","kind":"typeIdentifier","preciseIdentifier":"c:@M@ScanbotBarcodeScannerSDK@objc(cs)SBSDKUI2Color","text":"SBSDKUI2Color"},{"kind":"text","text":" *) "},{"kind":"internalParam","text":"sbColorSurface"},{"kind":"text","text":" "},{"kind":"identifier","text":"sbColorOutline:"},{"kind":"text","text":"("},{"identifier":"doc:\/\/net.doo.ScanbotBarcodeScannerSDK\/documentation\/ScanbotBarcodeScannerSDK\/SBSDKUI2Color","kind":"typeIdentifier","preciseIdentifier":"c:@M@ScanbotBarcodeScannerSDK@objc(cs)SBSDKUI2Color","text":"SBSDKUI2Color"},{"kind":"text","text":" *) "},{"kind":"internalParam","text":"sbColorOutline"},{"kind":"text","text":" "},{"kind":"identifier","text":"sbColorOnSurfaceVariant:"},{"kind":"text","text":"("},{"identifier":"doc:\/\/net.doo.ScanbotBarcodeScannerSDK\/documentation\/ScanbotBarcodeScannerSDK\/SBSDKUI2Color","kind":"typeIdentifier","preciseIdentifier":"c:@M@ScanbotBarcodeScannerSDK@objc(cs)SBSDKUI2Color","text":"SBSDKUI2Color"},{"kind":"text","text":" *) "},{"kind":"internalParam","text":"sbColorOnSurfaceVariant"},{"kind":"text","text":" "},{"kind":"identifier","text":"sbColorOnSurface:"},{"kind":"text","text":"("},{"identifier":"doc:\/\/net.doo.ScanbotBarcodeScannerSDK\/documentation\/ScanbotBarcodeScannerSDK\/SBSDKUI2Color","kind":"typeIdentifier","preciseIdentifier":"c:@M@ScanbotBarcodeScannerSDK@objc(cs)SBSDKUI2Color","text":"SBSDKUI2Color"},{"kind":"text","text":" *) "},{"kind":"internalParam","text":"sbColorOnSurface"},{"kind":"text","text":" "},{"kind":"identifier","text":"sbColorSurfaceLow:"},{"kind":"text","text":"("},{"identifier":"doc:\/\/net.doo.ScanbotBarcodeScannerSDK\/documentation\/ScanbotBarcodeScannerSDK\/SBSDKUI2Color","kind":"typeIdentifier","preciseIdentifier":"c:@M@ScanbotBarcodeScannerSDK@objc(cs)SBSDKUI2Color","text":"SBSDKUI2Color"},{"kind":"text","text":" *) "},{"kind":"internalParam","text":"sbColorSurfaceLow"},{"kind":"text","text":" "},{"kind":"identifier","text":"sbColorSurfaceHigh:"},{"kind":"text","text":"("},{"identifier":"doc:\/\/net.doo.ScanbotBarcodeScannerSDK\/documentation\/ScanbotBarcodeScannerSDK\/SBSDKUI2Color","kind":"typeIdentifier","preciseIdentifier":"c:@M@ScanbotBarcodeScannerSDK@objc(cs)SBSDKUI2Color","text":"SBSDKUI2Color"},{"kind":"text","text":" *) "},{"kind":"internalParam","text":"sbColorSurfaceHigh"},{"kind":"text","text":" "},{"kind":"identifier","text":"sbColorModalOverlay:"},{"kind":"text","text":"("},{"identifier":"doc:\/\/net.doo.ScanbotBarcodeScannerSDK\/documentation\/ScanbotBarcodeScannerSDK\/SBSDKUI2Color","kind":"typeIdentifier","preciseIdentifier":"c:@M@ScanbotBarcodeScannerSDK@objc(cs)SBSDKUI2Color","text":"SBSDKUI2Color"},{"kind":"text","text":" *) "},{"kind":"internalParam","text":"sbColorModalOverlay"},{"kind":"text","text":";"}],"platforms":["iOS"]}]}],"metadata":{"navigatorTitle":[{"kind":"identifier","text":"initWithSbColorPrimary:sbColorPrimaryDisabled:sbColorNegative:sbColorPositive:sbColorWarning:sbColorSecondary:sbColorSecondaryDisabled:sbColorOnPrimary:sbColorOnSecondary:sbColorSurface:sbColorOutline:sbColorOnSurfaceVariant:sbColorOnSurface:sbColorSurfaceLow:sbColorSurfaceHigh:sbColorModalOverlay:"}],"symbolKind":"method","role":"symbol","fragments":[{"text":"- ","kind":"text"},{"text":"initWithSbColorPrimary:sbColorPrimaryDisabled:sbColorNegative:sbColorPositive:sbColorWarning:sbColorSecondary:sbColorSecondaryDisabled:sbColorOnPrimary:sbColorOnSecondary:sbColorSurface:sbColorOutline:sbColorOnSurfaceVariant:sbColorOnSurface:sbColorSurfaceLow:sbColorSurfaceHigh:sbColorModalOverlay:","kind":"identifier"}],"title":"initWithSbColorPrimary:sbColorPrimaryDisabled:sbColorNegative:sbColorPositive:sbColorWarning:sbColorSecondary:sbColorSecondaryDisabled:sbColorOnPrimary:sbColorOnSecondary:sbColorSurface:sbColorOutline:sbColorOnSurfaceVariant:sbColorOnSurface:sbColorSurfaceLow:sbColorSurfaceHigh:sbColorModalOverlay:","externalID":"c:@M@ScanbotBarcodeScannerSDK@objc(cs)SBSDKUI2Palette(im)initWithSbColorPrimary:sbColorPrimaryDisabled:sbColorNegative:sbColorPositive:sbColorWarning:sbColorSecondary:sbColorSecondaryDisabled:sbColorOnPrimary:sbColorOnSecondary:sbColorSurface:sbColorOutline:sbColorOnSurfaceVariant:sbColorOnSurface:sbColorSurfaceLow:sbColorSurfaceHigh:sbColorModalOverlay:","roleHeading":"Instance Method","modules":[{"name":"ScanbotBarcodeScannerSDK"}]},"kind":"symbol","identifier":{"url":"doc:\/\/net.doo.ScanbotBarcodeScannerSDK\/documentation\/ScanbotBarcodeScannerSDK\/SBSDKUI2Palette\/initWithSbColorPrimary:sbColorPrimaryDisabled:sbColorNegative:sbColorPositive:sbColorWarning:sbColorSecondary:sbColorSecondaryDisabled:sbColorOnPrimary:sbColorOnSecondary:sbColorSurface:sbColorOutline:sbColorOnSurfaceVariant:sbColorOnSurface:sbColorSurfaceLow:sbColorSurfaceHigh:sbColorModalOverlay:","interfaceLanguage":"occ"},"sections":[],"schemaVersion":{"minor":3,"major":0,"patch":0},"variants":[{"paths":["\/documentation\/scanbotbarcodescannersdk\/sbsdkui2palette\/initwithsbcolorprimary:sbcolorprimarydisabled:sbcolornegative:sbcolorpositive:sbcolorwarning:sbcolorsecondary:sbcolorsecondarydisabled:sbcoloronprimary:sbcoloronsecondary:sbcolorsurface:sbcoloroutline:sbcoloronsurfacevariant:sbcoloronsurfac-8ll73"],"traits":[{"interfaceLanguage":"occ"}]}],"hierarchy":{"paths":[["doc:\/\/net.doo.ScanbotBarcodeScannerSDK\/documentation\/ScanbotBarcodeScannerSDK","doc:\/\/net.doo.ScanbotBarcodeScannerSDK\/documentation\/ScanbotBarcodeScannerSDK\/SBSDKUI2Palette"]]},"references":{"doc://net.doo.ScanbotBarcodeScannerSDK/documentation/ScanbotBarcodeScannerSDK/SBSDKUI2Palette/initWithSbColorPrimary:sbColorPrimaryDisabled:sbColorNegative:sbColorPositive:sbColorWarning:sbColorSecondary:sbColorSecondaryDisabled:sbColorOnPrimary:sbColorOnSecondary:sbColorSurface:sbColorOutline:sbColorOnSurfaceVariant:sbColorOnSurface:sbColorSurfaceLow:sbColorSurfaceHigh:sbColorModalOverlay:":{"type":"topic","title":"initWithSbColorPrimary:sbColorPrimaryDisabled:sbColorNegative:sbColorPositive:sbColorWarning:sbColorSecondary:sbColorSecondaryDisabled:sbColorOnPrimary:sbColorOnSecondary:sbColorSurface:sbColorOutline:sbColorOnSurfaceVariant:sbColorOnSurface:sbColorSurfaceLow:sbColorSurfaceHigh:sbColorModalOverlay:","navigatorTitle":[{"text":"initWithSbColorPrimary:sbColorPrimaryDisabled:sbColorNegative:sbColorPositive:sbColorWarning:sbColorSecondary:sbColorSecondaryDisabled:sbColorOnPrimary:sbColorOnSecondary:sbColorSurface:sbColorOutline:sbColorOnSurfaceVariant:sbColorOnSurface:sbColorSurfaceLow:sbColorSurfaceHigh:sbColorModalOverlay:","kind":"identifier"}],"abstract":[],"url":"\/documentation\/scanbotbarcodescannersdk\/sbsdkui2palette\/initwithsbcolorprimary:sbcolorprimarydisabled:sbcolornegative:sbcolorpositive:sbcolorwarning:sbcolorsecondary:sbcolorsecondarydisabled:sbcoloronprimary:sbcoloronsecondary:sbcolorsurface:sbcoloroutline:sbcoloronsurfacevariant:sbcoloronsurfac-8ll73","role":"symbol","fragments":[{"text":"- ","kind":"text"},{"text":"initWithSbColorPrimary:sbColorPrimaryDisabled:sbColorNegative:sbColorPositive:sbColorWarning:sbColorSecondary:sbColorSecondaryDisabled:sbColorOnPrimary:sbColorOnSecondary:sbColorSurface:sbColorOutline:sbColorOnSurfaceVariant:sbColorOnSurface:sbColorSurfaceLow:sbColorSurfaceHigh:sbColorModalOverlay:","kind":"identifier"}],"identifier":"doc:\/\/net.doo.ScanbotBarcodeScannerSDK\/documentation\/ScanbotBarcodeScannerSDK\/SBSDKUI2Palette\/initWithSbColorPrimary:sbColorPrimaryDisabled:sbColorNegative:sbColorPositive:sbColorWarning:sbColorSecondary:sbColorSecondaryDisabled:sbColorOnPrimary:sbColorOnSecondary:sbColorSurface:sbColorOutline:sbColorOnSurfaceVariant:sbColorOnSurface:sbColorSurfaceLow:sbColorSurfaceHigh:sbColorModalOverlay:","kind":"symbol"},"doc://net.doo.ScanbotBarcodeScannerSDK/documentation/ScanbotBarcodeScannerSDK/SBSDKUI2Color":{"identifier":"doc:\/\/net.doo.ScanbotBarcodeScannerSDK\/documentation\/ScanbotBarcodeScannerSDK\/SBSDKUI2Color","kind":"symbol","title":"SBSDKUI2Color","url":"\/documentation\/scanbotbarcodescannersdk\/sbsdkui2color","fragments":[{"text":"class","kind":"keyword"},{"text":" ","kind":"text"},{"text":"SBSDKUI2Color","kind":"identifier"}],"type":"topic","abstract":[],"role":"symbol","navigatorTitle":[{"text":"SBSDKUI2Color","kind":"identifier"}]},"doc://net.doo.ScanbotBarcodeScannerSDK/documentation/ScanbotBarcodeScannerSDK/SBSDKUI2Palette":{"type":"topic","navigatorTitle":[{"text":"SBSDKUI2Palette","kind":"identifier"}],"kind":"symbol","identifier":"doc:\/\/net.doo.ScanbotBarcodeScannerSDK\/documentation\/ScanbotBarcodeScannerSDK\/SBSDKUI2Palette","fragments":[{"text":"class","kind":"keyword"},{"text":" ","kind":"text"},{"text":"SBSDKUI2Palette","kind":"identifier"}],"title":"SBSDKUI2Palette","url":"\/documentation\/scanbotbarcodescannersdk\/sbsdkui2palette","abstract":[{"text":"Value palette describing the colors of the scanner screens.","type":"text"}],"role":"symbol"},"doc://net.doo.ScanbotBarcodeScannerSDK/documentation/ScanbotBarcodeScannerSDK":{"type":"topic","title":"ScanbotBarcodeScannerSDK","url":"\/documentation\/scanbotbarcodescannersdk","kind":"symbol","identifier":"doc:\/\/net.doo.ScanbotBarcodeScannerSDK\/documentation\/ScanbotBarcodeScannerSDK","abstract":[{"text":"Version: 7.0.1","type":"text"}],"role":"collection"}},"variantOverrides":[{"traits":[{"interfaceLanguage":"occ"}],"patch":[{"value":"SBSDKUI2Color","op":"replace","path":"\/references\/doc:~1~1net.doo.ScanbotBarcodeScannerSDK~1documentation~1ScanbotBarcodeScannerSDK~1SBSDKUI2Color\/title"},{"value":[{"text":"SBSDKUI2Color","kind":"identifier"}],"op":"replace","path":"\/references\/doc:~1~1net.doo.ScanbotBarcodeScannerSDK~1documentation~1ScanbotBarcodeScannerSDK~1SBSDKUI2Color\/fragments"},{"value":[{"kind":"identifier","text":"SBSDKUI2Color"}],"op":"replace","path":"\/references\/doc:~1~1net.doo.ScanbotBarcodeScannerSDK~1documentation~1ScanbotBarcodeScannerSDK~1SBSDKUI2Color\/navigatorTitle"},{"value":"SBSDKUI2Palette","op":"replace","path":"\/references\/doc:~1~1net.doo.ScanbotBarcodeScannerSDK~1documentation~1ScanbotBarcodeScannerSDK~1SBSDKUI2Palette\/title"},{"value":[{"text":"SBSDKUI2Palette","kind":"identifier"}],"op":"replace","path":"\/references\/doc:~1~1net.doo.ScanbotBarcodeScannerSDK~1documentation~1ScanbotBarcodeScannerSDK~1SBSDKUI2Palette\/fragments"},{"value":[{"text":"SBSDKUI2Palette","kind":"identifier"}],"op":"replace","path":"\/references\/doc:~1~1net.doo.ScanbotBarcodeScannerSDK~1documentation~1ScanbotBarcodeScannerSDK~1SBSDKUI2Palette\/navigatorTitle"}]}]}