{"schemaVersion":{"minor":3,"major":0,"patch":0},"variants":[{"traits":[{"interfaceLanguage":"swift"}],"paths":["\/documentation\/scanbotbarcodescannersdk\/sbsdkui2multiplescanningmode\/init(countingrepeatdelay:allowemptysubmission:mode:sheet:sheetcontent:manualcounteditdialog:barcodeinfomapping:aroverlay:)"]},{"paths":["\/documentation\/scanbotbarcodescannersdk\/sbsdkui2multiplescanningmode\/init(countingrepeatdelay:allowemptysubmission:mode:sheet:sheetcontent:manualcounteditdialog:barcodeinfomapping:aroverlay:)"],"traits":[{"interfaceLanguage":"occ"}]}],"primaryContentSections":[{"kind":"declarations","declarations":[{"languages":["swift"],"platforms":["iOS"],"tokens":[{"text":"init","kind":"keyword"},{"text":"(","kind":"text"},{"text":"countingRepeatDelay","kind":"externalParam"},{"kind":"text","text":": "},{"kind":"typeIdentifier","text":"Int","preciseIdentifier":"s:Si"},{"kind":"text","text":" = 1000, "},{"kind":"externalParam","text":"allowEmptySubmission"},{"text":": ","kind":"text"},{"preciseIdentifier":"s:Sb","text":"Bool","kind":"typeIdentifier"},{"kind":"text","text":" = false, "},{"text":"mode","kind":"externalParam"},{"text":": ","kind":"text"},{"kind":"typeIdentifier","identifier":"doc:\/\/net.doo.ScanbotBarcodeScannerSDK\/documentation\/ScanbotBarcodeScannerSDK\/SBSDKUI2MultipleBarcodesScanningMode","text":"SBSDKUI2MultipleBarcodesScanningMode","preciseIdentifier":"c:@M@ScanbotBarcodeScannerSDK@E@SBSDKUI2MultipleBarcodesScanningMode"},{"text":" = SBSDKUI2MultipleBarcodesScanningMode.counting, ","kind":"text"},{"kind":"externalParam","text":"sheet"},{"text":": ","kind":"text"},{"identifier":"doc:\/\/net.doo.ScanbotBarcodeScannerSDK\/documentation\/ScanbotBarcodeScannerSDK\/SBSDKUI2Sheet","preciseIdentifier":"c:@M@ScanbotBarcodeScannerSDK@objc(cs)SBSDKUI2Sheet","kind":"typeIdentifier","text":"SBSDKUI2Sheet"},{"kind":"text","text":" = SBSDKUI2Sheet(mode: SBSDKUI2SheetMode.collapsedSheet,\n                                                     collapsedVisibleHeight: SBSDKUI2CollapsedVisibleHeight.small,\n                                                     listButton: SBSDKUI2BadgedButton(badgeBackgroundColor: SBSDKUI2Color(colorString: \"?sbColorSurface\",\n                                                                                                                          isArgb: false),\n                                                                                      badgeForegroundColor: SBSDKUI2Color(colorString: \"?sbColorPrimary\",\n                                                                                                                          isArgb: false),\n                                                                                      visible: true,\n                                                                                      backgroundColor: SBSDKUI2Color(colorString: \"?sbColorSurfaceHigh\",\n                                                                                                                     isArgb: false),\n                                                                                      foregroundColor: SBSDKUI2Color(colorString: \"?sbColorOnPrimary\",\n                                                                                                                     isArgb: false),\n                                                                                      activeBackgroundColor: SBSDKUI2Color(colorString: \"?sbColorSurfaceHigh\",\n                                                                                                                           isArgb: false),\n                                                                                      activeForegroundColor: SBSDKUI2Color(colorString: \"?sbColorOnPrimary\",\n                                                                                                                           isArgb: false))), "},{"kind":"externalParam","text":"sheetContent"},{"text":": ","kind":"text"},{"preciseIdentifier":"c:@M@ScanbotBarcodeScannerSDK@objc(cs)SBSDKUI2SheetContent","text":"SBSDKUI2SheetContent","kind":"typeIdentifier","identifier":"doc:\/\/net.doo.ScanbotBarcodeScannerSDK\/documentation\/ScanbotBarcodeScannerSDK\/SBSDKUI2SheetContent"},{"kind":"text","text":" = SBSDKUI2SheetContent(sheetColor: SBSDKUI2Color(colorString: \"?sbColorSurface\", isArgb: false),\n                                         dividerColor: SBSDKUI2Color(colorString: \"?sbColorOutline\",\n                                                                     isArgb: false),\n                                         manualCountChangeEnabled: true,\n                                         manualCountOutlineColor: SBSDKUI2Color(colorString: \"?sbColorOutline\",\n                                                                                isArgb: false),\n                                         manualCountChangeColor: SBSDKUI2Color(colorString: \"?sbColorPrimary\",\n                                                                               isArgb: false),\n                                         title: SBSDKUI2StyledText(text: \"?multipleModeSheetTitle\",\n                                                                   color: SBSDKUI2Color(colorString: \"?sbColorOnSurface\",\n                                                                                        isArgb: false)),\n                                         clearAllButton: SBSDKUI2ButtonConfiguration(visible: true,\n                                                                                     text: \"?sheetClearAllButton\",\n                                                                                     background: SBSDKUI2BackgroundStyle(strokeColor: SBSDKUI2Color(colorString: \"#00000000\",\n                                                                                                                                                    isArgb: false),\n                                                                                                                         fillColor: SBSDKUI2Color(colorString: \"#00000000\",\n                                                                                                                                                  isArgb: false),\n                                                                                                                         strokeWidth: 1.0),\n                                                                                     foreground: SBSDKUI2ForegroundStyle(iconVisible: false,\n                                                                                                                         color: SBSDKUI2Color(colorString: \"?sbColorOnSurface\",\n                                                                                                                                              isArgb: false),\n                                                                                                                         useShadow: false)),\n                                         barcodeItemTitle: SBSDKUI2StyledText(visible: true,\n                                                                              text: \"BARCODE_TITLE\",\n                                                                              color: SBSDKUI2Color(colorString: \"?sbColorOnSurface\",\n                                                                                                   isArgb: false),\n                                                                              useShadow: false),\n                                         barcodeItemSubtitle: SBSDKUI2StyledText(visible: true,\n                                                                                 text: \"BARCODE_SUBTITLE\",\n                                                                                 color: SBSDKUI2Color(colorString: \"?sbColorOnSurfaceVariant\",\n                                                                                                      isArgb: false),\n                                                                                 useShadow: false),\n                                         barcodeItemImageVisible: true,\n                                         submitButton: SBSDKUI2ButtonConfiguration(visible: true,\n                                                                                   text: \"?sheetSubmitButton\",\n                                                                                   background: SBSDKUI2BackgroundStyle(strokeColor: SBSDKUI2Color(colorString: \"#00000000\",\n                                                                                                                                                  isArgb: false),\n                                                                                                                       fillColor: SBSDKUI2Color(colorString: \"#00000000\",\n                                                                                                                                                isArgb: false),\n                                                                                                                       strokeWidth: 1.0),\n                                                                                   foreground: SBSDKUI2ForegroundStyle(iconVisible: false,\n                                                                                                                       color: SBSDKUI2Color(colorString: \"?sbColorOnSurface\",\n                                                                                                                                            isArgb: false),\n                                                                                                                       useShadow: false)),\n                                         startScanningButton: SBSDKUI2ButtonConfiguration(visible: true,\n                                                                                          text: \"?sheetStartScanningButton\",\n                                                                                          background: SBSDKUI2BackgroundStyle(strokeColor: SBSDKUI2Color(colorString: \"?sbColorPrimary\",\n                                                                                                                                                         isArgb: false),\n                                                                                                                              fillColor: SBSDKUI2Color(colorString: \"?sbColorPrimary\",\n                                                                                                                                                       isArgb: false),\n                                                                                                                              strokeWidth: 1.0),\n                                                                                          foreground: SBSDKUI2ForegroundStyle(iconVisible: false,\n                                                                                                                              color: SBSDKUI2Color(colorString: \"?sbColorOnPrimary\",\n                                                                                                                                                   isArgb: false),\n                                                                                                                              useShadow: false)),\n                                         placeholderTitle: SBSDKUI2StyledText(visible: true,\n                                                                              text: \"?sheetPlaceholderTitle\",\n                                                                              color: SBSDKUI2Color(colorString: \"?sbColorOnSurface\",\n                                                                                                   isArgb: false),\n                                                                              useShadow: false),\n                                         placeholderSubtitle: SBSDKUI2StyledText(visible: true,\n                                                                                 text: \"?sheetPlaceholderSubtitle\",\n                                                                                 color: SBSDKUI2Color(colorString: \"?sbColorOnSurfaceVariant\",\n                                                                                                      isArgb: false),\n                                                                                 useShadow: false),\n                                         placeholderIconBackground: SBSDKUI2Color(colorString: \"?sbColorOutline\",\n                                                                                  isArgb: false),\n                                         placeholderIcon: SBSDKUI2IconStyle(visible: true,\n                                                                            color: SBSDKUI2Color(colorString: \"?sbColorOnSurface\",\n                                                                                                 isArgb: false)),\n                                         swipeToDelete: SBSDKUI2SwipeToDelete(enabled: true,\n                                                                              backgroundColor: SBSDKUI2Color(colorString: \"?sbColorNegative\",\n                                                                                                             isArgb: false),\n                                                                              iconColor: SBSDKUI2Color(colorString: \"?sbColorOnPrimary\",\n                                                                                                       isArgb: false))), "},{"kind":"externalParam","text":"manualCountEditDialog"},{"kind":"text","text":": "},{"text":"SBSDKUI2ManualCountEditDialog","kind":"typeIdentifier","identifier":"doc:\/\/net.doo.ScanbotBarcodeScannerSDK\/documentation\/ScanbotBarcodeScannerSDK\/SBSDKUI2ManualCountEditDialog","preciseIdentifier":"c:@M@ScanbotBarcodeScannerSDK@objc(cs)SBSDKUI2ManualCountEditDialog"},{"text":" = SBSDKUI2ManualCountEditDialog(sheetColor: SBSDKUI2Color(colorString: \"?sbColorSurface\",\n                                                                            isArgb: false),\n                                                  dividerColor: SBSDKUI2Color(colorString: \"?sbColorOutline\",\n                                                                              isArgb: false),\n                                                  modalOverlayColor: SBSDKUI2Color(colorString: \"?sbColorModalOverlay\",\n                                                                                   isArgb: false),\n                                                  title: SBSDKUI2StyledText(text: \"?manualCountEditDialogTitle\",\n                                                                            color: SBSDKUI2Color(colorString: \"?sbColorOnSurface\",\n                                                                                                 isArgb: false)),\n                                                  info: SBSDKUI2StyledText(text: \"?manualCountEditDialogInfo\",\n                                                                           color: SBSDKUI2Color(colorString: \"?sbColorOnSurfaceVariant\",\n                                                                                                isArgb: false)),\n                                                  updateButton: SBSDKUI2ButtonConfiguration(visible: true,\n                                                                                            text: \"?manualCountEditDialogUpdateButton\",\n                                                                                            background: SBSDKUI2BackgroundStyle(strokeColor: SBSDKUI2Color(colorString: \"?sbColorPrimary\",\n                                                                                                                                                           isArgb: false),\n                                                                                                                                fillColor: SBSDKUI2Color(colorString: \"?sbColorPrimary\",\n                                                                                                                                                         isArgb: false),\n                                                                                                                                strokeWidth: 1.0),\n                                                                                            foreground: SBSDKUI2ForegroundStyle(iconVisible: false,\n                                                                                                                                color: SBSDKUI2Color(colorString: \"?sbColorOnPrimary\",\n                                                                                                                                                     isArgb: false),\n                                                                                                                                useShadow: false)),\n                                                  cancelButton: SBSDKUI2ButtonConfiguration(visible: true,\n                                                                                            text: \"?manualCountEditDialogCancelButton\",\n                                                                                            background: SBSDKUI2BackgroundStyle(strokeColor: SBSDKUI2Color(colorString: \"#00000000\",\n                                                                                                                                                           isArgb: false),\n                                                                                                                                fillColor: SBSDKUI2Color(colorString: \"#00000000\",\n                                                                                                                                                         isArgb: false),\n                                                                                                                                strokeWidth: 1.0),\n                                                                                            foreground: SBSDKUI2ForegroundStyle(iconVisible: false,\n                                                                                                                                color: SBSDKUI2Color(colorString: \"?sbColorPrimary\",\n                                                                                                                                                     isArgb: false),\n                                                                                                                                useShadow: false)),\n                                                  clearTextButton: SBSDKUI2IconStyle(visible: true,\n                                                                                     color: SBSDKUI2Color(colorString: \"?sbColorOnSurfaceVariant\",\n                                                                                                          isArgb: false))), ","kind":"text"},{"text":"barcodeInfoMapping","kind":"externalParam"},{"text":": ","kind":"text"},{"kind":"typeIdentifier","preciseIdentifier":"c:@M@ScanbotBarcodeScannerSDK@objc(cs)SBSDKUI2BarcodeInfoMapping","text":"SBSDKUI2BarcodeInfoMapping","identifier":"doc:\/\/net.doo.ScanbotBarcodeScannerSDK\/documentation\/ScanbotBarcodeScannerSDK\/SBSDKUI2BarcodeInfoMapping"},{"text":" = SBSDKUI2BarcodeInfoMapping(sheetColor: SBSDKUI2Color(colorString: \"?sbColorSurface\", isArgb: false),\n                                               dividerColor: SBSDKUI2Color(colorString: \"?sbColorOutline\",\n                                                                           isArgb: false),\n                                               modalOverlayColor: SBSDKUI2Color(colorString: \"?sbColorModalOverlay\",\n                                                                                isArgb: false),\n                                               loadingMessage: SBSDKUI2StyledText(text: \"?barcodeInfoMappingLoadingMessage\",\n                                                                                  color: SBSDKUI2Color(colorString: \"?sbColorPrimary\",\n                                                                                                       isArgb: false)),\n                                               errorState: SBSDKUI2BarcodeItemErrorState(title: SBSDKUI2StyledText(text: \"?barcodeInfoMappingErrorStateTitle\",\n                                                                                                                   color: SBSDKUI2Color(colorString: \"?sbColorOnSurface\",\n                                                                                                                                        isArgb: false)),\n                                                                                         subtitle: SBSDKUI2StyledText(text: \"?barcodeInfoMappingErrorStateSubtitle\",\n                                                                                                                      color: SBSDKUI2Color(colorString: \"?sbColorOnSurfaceVariant\",\n                                                                                                                                           isArgb: false)),\n                                                                                         retryButton: SBSDKUI2ButtonConfiguration(visible: true,\n                                                                                                                                  text: \"?barcodeInfoMappingErrorStateRetryButton\",\n                                                                                                                                  background: SBSDKUI2BackgroundStyle(strokeColor: SBSDKUI2Color(colorString: \"?sbColorPrimary\",\n                                                                                                                                                                                                 isArgb: false),\n                                                                                                                                                                      fillColor: SBSDKUI2Color(colorString: \"?sbColorPrimary\",\n                                                                                                                                                                                               isArgb: false),\n                                                                                                                                                                      strokeWidth: 1.0),\n                                                                                                                                  foreground: SBSDKUI2ForegroundStyle(iconVisible: true,\n                                                                                                                                                                      color: SBSDKUI2Color(colorString: \"?sbColorOnPrimary\",\n                                                                                                                                                                                           isArgb: false),\n                                                                                                                                                                      useShadow: false)),\n                                                                                         cancelButton: SBSDKUI2ButtonConfiguration(visible: true,\n                                                                                                                                   text: \"?barcodeInfoMappingErrorStateCancelButton\",\n                                                                                                                                   background: SBSDKUI2BackgroundStyle(strokeColor: SBSDKUI2Color(colorString: \"#00000000\",\n                                                                                                                                                                                                  isArgb: false),\n                                                                                                                                                                       fillColor: SBSDKUI2Color(colorString: \"#00000000\",\n                                                                                                                                                                                                isArgb: false),\n                                                                                                                                                                       strokeWidth: 1.0),\n                                                                                                                                   foreground: SBSDKUI2ForegroundStyle(iconVisible: false,\n                                                                                                                                                                       color: SBSDKUI2Color(colorString: \"?sbColorPrimary\",\n                                                                                                                                                                                            isArgb: false),\n                                                                                                                                                                       useShadow: false)))), ","kind":"text"},{"text":"arOverlay","kind":"externalParam"},{"text":": ","kind":"text"},{"kind":"typeIdentifier","text":"SBSDKUI2ArOverlayGeneralConfiguration","preciseIdentifier":"c:@M@ScanbotBarcodeScannerSDK@objc(cs)SBSDKUI2ArOverlayGeneralConfiguration","identifier":"doc:\/\/net.doo.ScanbotBarcodeScannerSDK\/documentation\/ScanbotBarcodeScannerSDK\/SBSDKUI2ArOverlayGeneralConfiguration"},{"kind":"text","text":" = SBSDKUI2ArOverlayGeneralConfiguration(visible: false,\n                                                                                                         counterBadge: SBSDKUI2BadgeStyle(visible: true,\n                                                                                                                                          background: SBSDKUI2BackgroundStyle(strokeColor: SBSDKUI2Color(colorString: \"#FF000000\",\n                                                                                                                                                                                                         isArgb: false),\n                                                                                                                                                                              fillColor: SBSDKUI2Color(colorString: \"?sbColorPositive\",\n                                                                                                                                                                                                       isArgb: false),\n                                                                                                                                                                              strokeWidth: 0.0),\n                                                                                                                                          foregroundColor: SBSDKUI2Color(colorString: \"?sbColorOnSurface\",\n                                                                                                                                                                         isArgb: false)),\n                                                                                                         automaticSelectionEnabled: false,\n                                                                                                         barcodeItemInfoPosition: SBSDKUI2BarcodeItemInfoPosition\n                                                                                                             .below,\n                                                                                                         polygon: SBSDKUI2ArOverlayPolygonConfiguration(visible: true,\n                                                                                                                                                        deselected: SBSDKUI2PolygonStyle(strokeColor: SBSDKUI2Color(colorString: \"?sbColorSurface\",\n                                                                                                                                                                                                                    isArgb: false),\n                                                                                                                                                                                         fillColor: SBSDKUI2Color(colorString: \"#00000000\",\n                                                                                                                                                                                                                  isArgb: false),\n                                                                                                                                                                                         strokeWidth: 3.0,\n                                                                                                                                                                                         cornerRadius: 5.0),\n                                                                                                                                                        selected: SBSDKUI2PolygonStyle(strokeColor: SBSDKUI2Color(colorString: \"?sbColorPositive\",\n                                                                                                                                                                                                                  isArgb: false),\n                                                                                                                                                                                       fillColor: SBSDKUI2Color(colorString: \"#00000000\",\n                                                                                                                                                                                                                isArgb: false),\n                                                                                                                                                                                       strokeWidth: 3.0,\n                                                                                                                                                                                       cornerRadius: 5.0)),\n                                                                                                         barcodeItemConfiguration: SBSDKUI2BarcodeItemConfiguration(imageVisible: true,\n                                                                                                                                                                    titleSelected: SBSDKUI2StyledText(text: \"BARCODE_TITLE\",\n                                                                                                                                                                                                      color: SBSDKUI2Color(colorString: \"?sbColorOnSurface\",\n                                                                                                                                                                                                                           isArgb: false)),\n                                                                                                                                                                    subtitleSelected: SBSDKUI2StyledText(visible: true,\n                                                                                                                                                                                                         text: \"BARCODE_SUBTITLE\",\n                                                                                                                                                                                                         color: SBSDKUI2Color(colorString: \"?sbColorOnSurfaceVariant\",\n                                                                                                                                                                                                                              isArgb: false),\n                                                                                                                                                                                                         useShadow: false),\n                                                                                                                                                                    titleDeselected: SBSDKUI2StyledText(visible: true,\n                                                                                                                                                                                                        text: \"BARCODE_TITLE\",\n                                                                                                                                                                                                        color: SBSDKUI2Color(colorString: \"?sbColorOnSurface\",\n                                                                                                                                                                                                                             isArgb: false),\n                                                                                                                                                                                                        useShadow: false),\n                                                                                                                                                                    subtitleDeselected: SBSDKUI2StyledText(text: \"BARCODE_SUBTITLE\",\n                                                                                                                                                                                                           color: SBSDKUI2Color(colorString: \"?sbColorOnSurfaceVariant\",\n                                                                                                                                                                                                                                isArgb: false)),\n                                                                                                                                                                    backgroundSelected: SBSDKUI2PolygonStyle(strokeColor: SBSDKUI2Color(colorString: \"?sbColorPositive\",\n                                                                                                                                                                                                                                        isArgb: false),\n                                                                                                                                                                                                             fillColor: SBSDKUI2Color(colorString: \"?sbColorPositive\",\n                                                                                                                                                                                                                                      isArgb: false),\n                                                                                                                                                                                                             strokeWidth: 1.0,\n                                                                                                                                                                                                             cornerRadius: 5.0),\n                                                                                                                                                                    backgroundDeselected: SBSDKUI2PolygonStyle(strokeColor: SBSDKUI2Color(colorString: \"?sbColorSurface\",\n                                                                                                                                                                                                                                          isArgb: false),\n                                                                                                                                                                                                               fillColor: SBSDKUI2Color(colorString: \"?sbColorSurface\",\n                                                                                                                                                                                                                                        isArgb: false),\n                                                                                                                                                                                                               strokeWidth: 1.0,\n                                                                                                                                                                                                               cornerRadius: 5.0))))"}]}]}],"sections":[],"kind":"symbol","metadata":{"modules":[{"name":"ScanbotBarcodeScannerSDK"}],"fragments":[{"kind":"identifier","text":"init"},{"text":"(","kind":"text"},{"kind":"externalParam","text":"countingRepeatDelay"},{"text":": ","kind":"text"},{"kind":"typeIdentifier","text":"Int","preciseIdentifier":"s:Si"},{"kind":"text","text":", "},{"text":"allowEmptySubmission","kind":"externalParam"},{"text":": ","kind":"text"},{"text":"Bool","kind":"typeIdentifier","preciseIdentifier":"s:Sb"},{"text":", ","kind":"text"},{"text":"mode","kind":"externalParam"},{"text":": ","kind":"text"},{"kind":"typeIdentifier","preciseIdentifier":"c:@M@ScanbotBarcodeScannerSDK@E@SBSDKUI2MultipleBarcodesScanningMode","text":"SBSDKUI2MultipleBarcodesScanningMode"},{"text":", ","kind":"text"},{"text":"sheet","kind":"externalParam"},{"kind":"text","text":": "},{"text":"SBSDKUI2Sheet","preciseIdentifier":"c:@M@ScanbotBarcodeScannerSDK@objc(cs)SBSDKUI2Sheet","kind":"typeIdentifier"},{"kind":"text","text":", "},{"text":"sheetContent","kind":"externalParam"},{"text":": ","kind":"text"},{"kind":"typeIdentifier","preciseIdentifier":"c:@M@ScanbotBarcodeScannerSDK@objc(cs)SBSDKUI2SheetContent","text":"SBSDKUI2SheetContent"},{"kind":"text","text":", "},{"text":"manualCountEditDialog","kind":"externalParam"},{"kind":"text","text":": "},{"text":"SBSDKUI2ManualCountEditDialog","preciseIdentifier":"c:@M@ScanbotBarcodeScannerSDK@objc(cs)SBSDKUI2ManualCountEditDialog","kind":"typeIdentifier"},{"text":", ","kind":"text"},{"text":"barcodeInfoMapping","kind":"externalParam"},{"text":": ","kind":"text"},{"text":"SBSDKUI2BarcodeInfoMapping","kind":"typeIdentifier","preciseIdentifier":"c:@M@ScanbotBarcodeScannerSDK@objc(cs)SBSDKUI2BarcodeInfoMapping"},{"text":", ","kind":"text"},{"kind":"externalParam","text":"arOverlay"},{"kind":"text","text":": "},{"preciseIdentifier":"c:@M@ScanbotBarcodeScannerSDK@objc(cs)SBSDKUI2ArOverlayGeneralConfiguration","text":"SBSDKUI2ArOverlayGeneralConfiguration","kind":"typeIdentifier"},{"kind":"text","text":")"}],"navigatorTitle":[{"text":"initWithCountingRepeatDelay:allowEmptySubmission:mode:sheet:sheetContent:manualCountEditDialog:barcodeInfoMapping:arOverlay:","kind":"identifier"}],"role":"symbol","symbolKind":"init","title":"init(countingRepeatDelay:allowEmptySubmission:mode:sheet:sheetContent:manualCountEditDialog:barcodeInfoMapping:arOverlay:)","roleHeading":"Initializer","externalID":"c:@M@ScanbotBarcodeScannerSDK@objc(cs)SBSDKUI2MultipleScanningMode(im)initWithCountingRepeatDelay:allowEmptySubmission:mode:sheet:sheetContent:manualCountEditDialog:barcodeInfoMapping:arOverlay:"},"identifier":{"interfaceLanguage":"swift","url":"doc:\/\/net.doo.ScanbotBarcodeScannerSDK\/documentation\/ScanbotBarcodeScannerSDK\/SBSDKUI2MultipleScanningMode\/init(countingRepeatDelay:allowEmptySubmission:mode:sheet:sheetContent:manualCountEditDialog:barcodeInfoMapping:arOverlay:)"},"hierarchy":{"paths":[["doc:\/\/net.doo.ScanbotBarcodeScannerSDK\/documentation\/ScanbotBarcodeScannerSDK","doc:\/\/net.doo.ScanbotBarcodeScannerSDK\/documentation\/ScanbotBarcodeScannerSDK\/SBSDKUI2MultipleScanningMode"]]},"references":{"doc://net.doo.ScanbotBarcodeScannerSDK/documentation/ScanbotBarcodeScannerSDK/SBSDKUI2ArOverlayGeneralConfiguration":{"role":"symbol","type":"topic","fragments":[{"kind":"keyword","text":"class"},{"text":" ","kind":"text"},{"text":"SBSDKUI2ArOverlayGeneralConfiguration","kind":"identifier"}],"url":"\/documentation\/scanbotbarcodescannersdk\/sbsdkui2aroverlaygeneralconfiguration","identifier":"doc:\/\/net.doo.ScanbotBarcodeScannerSDK\/documentation\/ScanbotBarcodeScannerSDK\/SBSDKUI2ArOverlayGeneralConfiguration","abstract":[{"text":"Configuration of the AR overlay displayed on top of barcodes in the camera preview.","type":"text"}],"kind":"symbol","navigatorTitle":[{"text":"SBSDKUI2ArOverlayGeneralConfiguration","kind":"identifier"}],"title":"SBSDKUI2ArOverlayGeneralConfiguration"},"doc://net.doo.ScanbotBarcodeScannerSDK/documentation/ScanbotBarcodeScannerSDK/SBSDKUI2Sheet":{"navigatorTitle":[{"text":"SBSDKUI2Sheet","kind":"identifier"}],"fragments":[{"text":"class","kind":"keyword"},{"kind":"text","text":" "},{"text":"SBSDKUI2Sheet","kind":"identifier"}],"kind":"symbol","abstract":[{"text":"Configuration of the preview mode for scanning multiple barcodes.","type":"text"}],"type":"topic","url":"\/documentation\/scanbotbarcodescannersdk\/sbsdkui2sheet","role":"symbol","title":"SBSDKUI2Sheet","identifier":"doc:\/\/net.doo.ScanbotBarcodeScannerSDK\/documentation\/ScanbotBarcodeScannerSDK\/SBSDKUI2Sheet"},"doc://net.doo.ScanbotBarcodeScannerSDK/documentation/ScanbotBarcodeScannerSDK/SBSDKUI2SheetContent":{"fragments":[{"kind":"keyword","text":"class"},{"kind":"text","text":" "},{"text":"SBSDKUI2SheetContent","kind":"identifier"}],"abstract":[{"type":"text","text":"Configuration of the list containing the barcodes that have already been scanned."}],"navigatorTitle":[{"text":"SBSDKUI2SheetContent","kind":"identifier"}],"identifier":"doc:\/\/net.doo.ScanbotBarcodeScannerSDK\/documentation\/ScanbotBarcodeScannerSDK\/SBSDKUI2SheetContent","type":"topic","role":"symbol","kind":"symbol","url":"\/documentation\/scanbotbarcodescannersdk\/sbsdkui2sheetcontent","title":"SBSDKUI2SheetContent"},"doc://net.doo.ScanbotBarcodeScannerSDK/documentation/ScanbotBarcodeScannerSDK/SBSDKUI2ManualCountEditDialog":{"navigatorTitle":[{"text":"SBSDKUI2ManualCountEditDialog","kind":"identifier"}],"abstract":[{"text":"Configuration of the dialog to manually edit the barcode count.","type":"text"}],"kind":"symbol","role":"symbol","identifier":"doc:\/\/net.doo.ScanbotBarcodeScannerSDK\/documentation\/ScanbotBarcodeScannerSDK\/SBSDKUI2ManualCountEditDialog","title":"SBSDKUI2ManualCountEditDialog","type":"topic","url":"\/documentation\/scanbotbarcodescannersdk\/sbsdkui2manualcounteditdialog","fragments":[{"kind":"keyword","text":"class"},{"kind":"text","text":" "},{"text":"SBSDKUI2ManualCountEditDialog","kind":"identifier"}]},"doc://net.doo.ScanbotBarcodeScannerSDK/documentation/ScanbotBarcodeScannerSDK/SBSDKUI2MultipleBarcodesScanningMode":{"url":"\/documentation\/scanbotbarcodescannersdk\/sbsdkui2multiplebarcodesscanningmode","identifier":"doc:\/\/net.doo.ScanbotBarcodeScannerSDK\/documentation\/ScanbotBarcodeScannerSDK\/SBSDKUI2MultipleBarcodesScanningMode","kind":"symbol","navigatorTitle":[{"kind":"identifier","text":"SBSDKUI2MultipleBarcodesScanningMode"}],"type":"topic","abstract":[{"type":"text","text":"Configuration of the mode used for scanning multiple barcodes."}],"fragments":[{"text":"enum","kind":"keyword"},{"kind":"text","text":" "},{"text":"SBSDKUI2MultipleBarcodesScanningMode","kind":"identifier"}],"role":"symbol","title":"SBSDKUI2MultipleBarcodesScanningMode"},"doc://net.doo.ScanbotBarcodeScannerSDK/documentation/ScanbotBarcodeScannerSDK/SBSDKUI2MultipleScanningMode/init(countingRepeatDelay:allowEmptySubmission:mode:sheet:sheetContent:manualCountEditDialog:barcodeInfoMapping:arOverlay:)":{"identifier":"doc:\/\/net.doo.ScanbotBarcodeScannerSDK\/documentation\/ScanbotBarcodeScannerSDK\/SBSDKUI2MultipleScanningMode\/init(countingRepeatDelay:allowEmptySubmission:mode:sheet:sheetContent:manualCountEditDialog:barcodeInfoMapping:arOverlay:)","fragments":[{"kind":"identifier","text":"init"},{"kind":"text","text":"("},{"text":"countingRepeatDelay","kind":"externalParam"},{"kind":"text","text":": "},{"text":"Int","kind":"typeIdentifier","preciseIdentifier":"s:Si"},{"text":", ","kind":"text"},{"kind":"externalParam","text":"allowEmptySubmission"},{"kind":"text","text":": "},{"preciseIdentifier":"s:Sb","text":"Bool","kind":"typeIdentifier"},{"kind":"text","text":", "},{"text":"mode","kind":"externalParam"},{"kind":"text","text":": "},{"preciseIdentifier":"c:@M@ScanbotBarcodeScannerSDK@E@SBSDKUI2MultipleBarcodesScanningMode","text":"SBSDKUI2MultipleBarcodesScanningMode","kind":"typeIdentifier"},{"text":", ","kind":"text"},{"text":"sheet","kind":"externalParam"},{"text":": ","kind":"text"},{"preciseIdentifier":"c:@M@ScanbotBarcodeScannerSDK@objc(cs)SBSDKUI2Sheet","kind":"typeIdentifier","text":"SBSDKUI2Sheet"},{"kind":"text","text":", "},{"kind":"externalParam","text":"sheetContent"},{"text":": ","kind":"text"},{"preciseIdentifier":"c:@M@ScanbotBarcodeScannerSDK@objc(cs)SBSDKUI2SheetContent","kind":"typeIdentifier","text":"SBSDKUI2SheetContent"},{"text":", ","kind":"text"},{"kind":"externalParam","text":"manualCountEditDialog"},{"text":": ","kind":"text"},{"text":"SBSDKUI2ManualCountEditDialog","kind":"typeIdentifier","preciseIdentifier":"c:@M@ScanbotBarcodeScannerSDK@objc(cs)SBSDKUI2ManualCountEditDialog"},{"kind":"text","text":", "},{"text":"barcodeInfoMapping","kind":"externalParam"},{"text":": ","kind":"text"},{"kind":"typeIdentifier","text":"SBSDKUI2BarcodeInfoMapping","preciseIdentifier":"c:@M@ScanbotBarcodeScannerSDK@objc(cs)SBSDKUI2BarcodeInfoMapping"},{"kind":"text","text":", "},{"kind":"externalParam","text":"arOverlay"},{"kind":"text","text":": "},{"text":"SBSDKUI2ArOverlayGeneralConfiguration","kind":"typeIdentifier","preciseIdentifier":"c:@M@ScanbotBarcodeScannerSDK@objc(cs)SBSDKUI2ArOverlayGeneralConfiguration"},{"kind":"text","text":")"}],"abstract":[],"navigatorTitle":[{"kind":"identifier","text":"initWithCountingRepeatDelay:allowEmptySubmission:mode:sheet:sheetContent:manualCountEditDialog:barcodeInfoMapping:arOverlay:"}],"type":"topic","kind":"symbol","title":"init(countingRepeatDelay:allowEmptySubmission:mode:sheet:sheetContent:manualCountEditDialog:barcodeInfoMapping:arOverlay:)","role":"symbol","url":"\/documentation\/scanbotbarcodescannersdk\/sbsdkui2multiplescanningmode\/init(countingrepeatdelay:allowemptysubmission:mode:sheet:sheetcontent:manualcounteditdialog:barcodeinfomapping:aroverlay:)"},"doc://net.doo.ScanbotBarcodeScannerSDK/documentation/ScanbotBarcodeScannerSDK/SBSDKUI2MultipleScanningMode":{"identifier":"doc:\/\/net.doo.ScanbotBarcodeScannerSDK\/documentation\/ScanbotBarcodeScannerSDK\/SBSDKUI2MultipleScanningMode","kind":"symbol","abstract":[{"text":"Configuration of the mode for scanning multiple barcodes.","type":"text"}],"role":"symbol","type":"topic","fragments":[{"text":"class","kind":"keyword"},{"text":" ","kind":"text"},{"text":"SBSDKUI2MultipleScanningMode","kind":"identifier"}],"title":"SBSDKUI2MultipleScanningMode","url":"\/documentation\/scanbotbarcodescannersdk\/sbsdkui2multiplescanningmode","navigatorTitle":[{"kind":"identifier","text":"SBSDKUI2MultipleScanningMode"}]},"doc://net.doo.ScanbotBarcodeScannerSDK/documentation/ScanbotBarcodeScannerSDK/SBSDKUI2BarcodeInfoMapping":{"role":"symbol","url":"\/documentation\/scanbotbarcodescannersdk\/sbsdkui2barcodeinfomapping","type":"topic","fragments":[{"kind":"keyword","text":"class"},{"kind":"text","text":" "},{"text":"SBSDKUI2BarcodeInfoMapping","kind":"identifier"}],"identifier":"doc:\/\/net.doo.ScanbotBarcodeScannerSDK\/documentation\/ScanbotBarcodeScannerSDK\/SBSDKUI2BarcodeInfoMapping","kind":"symbol","abstract":[{"type":"text","text":"Configuration of the barcode data mapping."}],"title":"SBSDKUI2BarcodeInfoMapping","navigatorTitle":[{"kind":"identifier","text":"SBSDKUI2BarcodeInfoMapping"}]},"doc://net.doo.ScanbotBarcodeScannerSDK/documentation/ScanbotBarcodeScannerSDK":{"kind":"symbol","type":"topic","url":"\/documentation\/scanbotbarcodescannersdk","identifier":"doc:\/\/net.doo.ScanbotBarcodeScannerSDK\/documentation\/ScanbotBarcodeScannerSDK","title":"ScanbotBarcodeScannerSDK","role":"collection","abstract":[{"type":"text","text":"Version: 6.2.0"}]}},"variantOverrides":[{"traits":[{"interfaceLanguage":"occ"}],"patch":[{"value":"occ","op":"replace","path":"\/identifier\/interfaceLanguage"},{"op":"replace","path":"\/metadata\/roleHeading","value":"Instance Method"},{"op":"replace","path":"\/metadata\/title","value":"initWithCountingRepeatDelay:allowEmptySubmission:mode:sheet:sheetContent:manualCountEditDialog:barcodeInfoMapping:arOverlay:"},{"value":"method","path":"\/metadata\/symbolKind","op":"replace"},{"op":"replace","path":"\/metadata\/fragments","value":[{"kind":"text","text":"- "},{"text":"initWithCountingRepeatDelay:allowEmptySubmission:mode:sheet:sheetContent:manualCountEditDialog:barcodeInfoMapping:arOverlay:","kind":"identifier"}]},{"path":"\/topicSections","op":"add","value":null},{"value":null,"op":"add","path":"\/relationshipsSections"},{"path":"\/seeAlsoSections","value":null,"op":"add"},{"op":"replace","path":"\/primaryContentSections\/0","value":{"kind":"declarations","declarations":[{"platforms":["iOS"],"tokens":[{"text":"- (","kind":"text"},{"preciseIdentifier":"c:*Qo","kind":"typeIdentifier","text":"id"},{"text":") ","kind":"text"},{"kind":"identifier","text":"initWithCountingRepeatDelay:"},{"kind":"text","text":"("},{"text":"NSInteger","kind":"typeIdentifier","preciseIdentifier":"c:@T@NSInteger"},{"text":") ","kind":"text"},{"kind":"internalParam","text":"countingRepeatDelay"},{"text":" ","kind":"text"},{"kind":"identifier","text":"allowEmptySubmission:"},{"text":"(","kind":"text"},{"preciseIdentifier":"c:@T@BOOL","text":"BOOL","kind":"typeIdentifier"},{"kind":"text","text":") "},{"text":"allowEmptySubmission","kind":"internalParam"},{"text":" ","kind":"text"},{"text":"mode:","kind":"identifier"},{"text":"(","kind":"text"},{"text":"enum","kind":"keyword"},{"text":" ","kind":"text"},{"kind":"typeIdentifier","text":"SBSDKUI2MultipleBarcodesScanningMode","preciseIdentifier":"c:@M@ScanbotBarcodeScannerSDK@E@SBSDKUI2MultipleBarcodesScanningMode","identifier":"doc:\/\/net.doo.ScanbotBarcodeScannerSDK\/documentation\/ScanbotBarcodeScannerSDK\/SBSDKUI2MultipleBarcodesScanningMode"},{"kind":"text","text":") "},{"kind":"internalParam","text":"mode"},{"text":" ","kind":"text"},{"kind":"identifier","text":"sheet:"},{"text":"(","kind":"text"},{"kind":"typeIdentifier","text":"SBSDKUI2Sheet","identifier":"doc:\/\/net.doo.ScanbotBarcodeScannerSDK\/documentation\/ScanbotBarcodeScannerSDK\/SBSDKUI2Sheet","preciseIdentifier":"c:@M@ScanbotBarcodeScannerSDK@objc(cs)SBSDKUI2Sheet"},{"kind":"text","text":" *) "},{"text":"sheet","kind":"internalParam"},{"text":" ","kind":"text"},{"kind":"identifier","text":"sheetContent:"},{"text":"(","kind":"text"},{"preciseIdentifier":"c:@M@ScanbotBarcodeScannerSDK@objc(cs)SBSDKUI2SheetContent","kind":"typeIdentifier","identifier":"doc:\/\/net.doo.ScanbotBarcodeScannerSDK\/documentation\/ScanbotBarcodeScannerSDK\/SBSDKUI2SheetContent","text":"SBSDKUI2SheetContent"},{"text":" *) ","kind":"text"},{"text":"sheetContent","kind":"internalParam"},{"text":" ","kind":"text"},{"text":"manualCountEditDialog:","kind":"identifier"},{"text":"(","kind":"text"},{"preciseIdentifier":"c:@M@ScanbotBarcodeScannerSDK@objc(cs)SBSDKUI2ManualCountEditDialog","kind":"typeIdentifier","identifier":"doc:\/\/net.doo.ScanbotBarcodeScannerSDK\/documentation\/ScanbotBarcodeScannerSDK\/SBSDKUI2ManualCountEditDialog","text":"SBSDKUI2ManualCountEditDialog"},{"kind":"text","text":" *) "},{"kind":"internalParam","text":"manualCountEditDialog"},{"kind":"text","text":" "},{"text":"barcodeInfoMapping:","kind":"identifier"},{"kind":"text","text":"("},{"text":"SBSDKUI2BarcodeInfoMapping","kind":"typeIdentifier","preciseIdentifier":"c:@M@ScanbotBarcodeScannerSDK@objc(cs)SBSDKUI2BarcodeInfoMapping","identifier":"doc:\/\/net.doo.ScanbotBarcodeScannerSDK\/documentation\/ScanbotBarcodeScannerSDK\/SBSDKUI2BarcodeInfoMapping"},{"kind":"text","text":" *) "},{"text":"barcodeInfoMapping","kind":"internalParam"},{"kind":"text","text":" "},{"text":"arOverlay:","kind":"identifier"},{"text":"(","kind":"text"},{"kind":"typeIdentifier","text":"SBSDKUI2ArOverlayGeneralConfiguration","preciseIdentifier":"c:@M@ScanbotBarcodeScannerSDK@objc(cs)SBSDKUI2ArOverlayGeneralConfiguration","identifier":"doc:\/\/net.doo.ScanbotBarcodeScannerSDK\/documentation\/ScanbotBarcodeScannerSDK\/SBSDKUI2ArOverlayGeneralConfiguration"},{"text":" *) ","kind":"text"},{"kind":"internalParam","text":"arOverlay"},{"text":";","kind":"text"}],"languages":["occ"]}]}},{"path":"\/references\/doc:~1~1net.doo.ScanbotBarcodeScannerSDK~1documentation~1ScanbotBarcodeScannerSDK~1SBSDKUI2ArOverlayGeneralConfiguration\/title","value":"SBSDKUI2ArOverlayGeneralConfiguration","op":"replace"},{"op":"replace","path":"\/references\/doc:~1~1net.doo.ScanbotBarcodeScannerSDK~1documentation~1ScanbotBarcodeScannerSDK~1SBSDKUI2ArOverlayGeneralConfiguration\/fragments","value":[{"kind":"identifier","text":"SBSDKUI2ArOverlayGeneralConfiguration"}]},{"op":"replace","value":[{"text":"SBSDKUI2ArOverlayGeneralConfiguration","kind":"identifier"}],"path":"\/references\/doc:~1~1net.doo.ScanbotBarcodeScannerSDK~1documentation~1ScanbotBarcodeScannerSDK~1SBSDKUI2ArOverlayGeneralConfiguration\/navigatorTitle"},{"op":"replace","path":"\/references\/doc:~1~1net.doo.ScanbotBarcodeScannerSDK~1documentation~1ScanbotBarcodeScannerSDK~1SBSDKUI2Sheet\/title","value":"SBSDKUI2Sheet"},{"op":"replace","path":"\/references\/doc:~1~1net.doo.ScanbotBarcodeScannerSDK~1documentation~1ScanbotBarcodeScannerSDK~1SBSDKUI2Sheet\/fragments","value":[{"kind":"identifier","text":"SBSDKUI2Sheet"}]},{"value":[{"kind":"identifier","text":"SBSDKUI2Sheet"}],"path":"\/references\/doc:~1~1net.doo.ScanbotBarcodeScannerSDK~1documentation~1ScanbotBarcodeScannerSDK~1SBSDKUI2Sheet\/navigatorTitle","op":"replace"},{"path":"\/references\/doc:~1~1net.doo.ScanbotBarcodeScannerSDK~1documentation~1ScanbotBarcodeScannerSDK~1SBSDKUI2SheetContent\/title","value":"SBSDKUI2SheetContent","op":"replace"},{"value":[{"text":"SBSDKUI2SheetContent","kind":"identifier"}],"op":"replace","path":"\/references\/doc:~1~1net.doo.ScanbotBarcodeScannerSDK~1documentation~1ScanbotBarcodeScannerSDK~1SBSDKUI2SheetContent\/fragments"},{"value":[{"kind":"identifier","text":"SBSDKUI2SheetContent"}],"path":"\/references\/doc:~1~1net.doo.ScanbotBarcodeScannerSDK~1documentation~1ScanbotBarcodeScannerSDK~1SBSDKUI2SheetContent\/navigatorTitle","op":"replace"},{"op":"replace","value":"SBSDKUI2ManualCountEditDialog","path":"\/references\/doc:~1~1net.doo.ScanbotBarcodeScannerSDK~1documentation~1ScanbotBarcodeScannerSDK~1SBSDKUI2ManualCountEditDialog\/title"},{"path":"\/references\/doc:~1~1net.doo.ScanbotBarcodeScannerSDK~1documentation~1ScanbotBarcodeScannerSDK~1SBSDKUI2ManualCountEditDialog\/fragments","value":[{"text":"SBSDKUI2ManualCountEditDialog","kind":"identifier"}],"op":"replace"},{"value":[{"text":"SBSDKUI2ManualCountEditDialog","kind":"identifier"}],"path":"\/references\/doc:~1~1net.doo.ScanbotBarcodeScannerSDK~1documentation~1ScanbotBarcodeScannerSDK~1SBSDKUI2ManualCountEditDialog\/navigatorTitle","op":"replace"},{"op":"replace","path":"\/references\/doc:~1~1net.doo.ScanbotBarcodeScannerSDK~1documentation~1ScanbotBarcodeScannerSDK~1SBSDKUI2MultipleBarcodesScanningMode\/title","value":"SBSDKUI2MultipleBarcodesScanningMode"},{"op":"replace","path":"\/references\/doc:~1~1net.doo.ScanbotBarcodeScannerSDK~1documentation~1ScanbotBarcodeScannerSDK~1SBSDKUI2MultipleBarcodesScanningMode\/fragments","value":[{"text":"SBSDKUI2MultipleBarcodesScanningMode","kind":"identifier"}]},{"op":"replace","value":[{"kind":"identifier","text":"SBSDKUI2MultipleBarcodesScanningMode"}],"path":"\/references\/doc:~1~1net.doo.ScanbotBarcodeScannerSDK~1documentation~1ScanbotBarcodeScannerSDK~1SBSDKUI2MultipleBarcodesScanningMode\/navigatorTitle"},{"path":"\/references\/doc:~1~1net.doo.ScanbotBarcodeScannerSDK~1documentation~1ScanbotBarcodeScannerSDK~1SBSDKUI2MultipleScanningMode~1init(countingRepeatDelay:allowEmptySubmission:mode:sheet:sheetContent:manualCountEditDialog:barcodeInfoMapping:arOverlay:)\/title","op":"replace","value":"initWithCountingRepeatDelay:allowEmptySubmission:mode:sheet:sheetContent:manualCountEditDialog:barcodeInfoMapping:arOverlay:"},{"path":"\/references\/doc:~1~1net.doo.ScanbotBarcodeScannerSDK~1documentation~1ScanbotBarcodeScannerSDK~1SBSDKUI2MultipleScanningMode~1init(countingRepeatDelay:allowEmptySubmission:mode:sheet:sheetContent:manualCountEditDialog:barcodeInfoMapping:arOverlay:)\/fragments","value":[{"text":"- ","kind":"text"},{"text":"initWithCountingRepeatDelay:allowEmptySubmission:mode:sheet:sheetContent:manualCountEditDialog:barcodeInfoMapping:arOverlay:","kind":"identifier"}],"op":"replace"},{"op":"replace","value":"SBSDKUI2MultipleScanningMode","path":"\/references\/doc:~1~1net.doo.ScanbotBarcodeScannerSDK~1documentation~1ScanbotBarcodeScannerSDK~1SBSDKUI2MultipleScanningMode\/title"},{"op":"replace","path":"\/references\/doc:~1~1net.doo.ScanbotBarcodeScannerSDK~1documentation~1ScanbotBarcodeScannerSDK~1SBSDKUI2MultipleScanningMode\/fragments","value":[{"kind":"identifier","text":"SBSDKUI2MultipleScanningMode"}]},{"op":"replace","path":"\/references\/doc:~1~1net.doo.ScanbotBarcodeScannerSDK~1documentation~1ScanbotBarcodeScannerSDK~1SBSDKUI2MultipleScanningMode\/navigatorTitle","value":[{"text":"SBSDKUI2MultipleScanningMode","kind":"identifier"}]},{"value":"SBSDKUI2BarcodeInfoMapping","path":"\/references\/doc:~1~1net.doo.ScanbotBarcodeScannerSDK~1documentation~1ScanbotBarcodeScannerSDK~1SBSDKUI2BarcodeInfoMapping\/title","op":"replace"},{"op":"replace","value":[{"kind":"identifier","text":"SBSDKUI2BarcodeInfoMapping"}],"path":"\/references\/doc:~1~1net.doo.ScanbotBarcodeScannerSDK~1documentation~1ScanbotBarcodeScannerSDK~1SBSDKUI2BarcodeInfoMapping\/fragments"},{"op":"replace","path":"\/references\/doc:~1~1net.doo.ScanbotBarcodeScannerSDK~1documentation~1ScanbotBarcodeScannerSDK~1SBSDKUI2BarcodeInfoMapping\/navigatorTitle","value":[{"text":"SBSDKUI2BarcodeInfoMapping","kind":"identifier"}]}]}]}